{"status": "OK", "copyright": "Copyright (c) 2019 The New York Times Company.  All Rights Reserved.", "num_results": 20, "last_modified": "2017-03-21T13:38:01-04:00", "results": {"list_name": "Combined Print and E-Book Fiction", "list_name_encoded": "combined-print-and-e-book-fiction", "bestsellers_date": "2015-02-28", "published_date": "2015-03-15", "published_date_description": "", "next_published_date": "2015-03-22", "previous_published_date": "2015-03-08", "display_name": "Combined Print & E-Book Fiction", "normal_list_ends_at": 15, "updated": "WEEKLY", "books": [{"rank": 1, "rank_last_week": 1, "weeks_on_list": 7, "asterisk": 0, "dagger": 0, "primary_isbn10": "0698185390", "primary_isbn13": "9780698185395", "publisher": "Riverhead", "description": "A psychological thriller set in London is full of complications and betrayals.", "price": 0, "title": "THE GIRL ON THE TRAIN", "author": "Paula Hawkins", "contributor": "by Paula Hawkins", "contributor_note": "", "book_image": "https://s1.nyt.com/du/books/images/9781594633669.jpg", "book_image_width": 312, "book_image_height": 495, "amazon_product_url": "http://www.amazon.com/The-Girl-Train-A-Novel-ebook/dp/B00L9B7IKE?tag=NYTBS-20", "age_group": "", "book_review_link": "https://www.nytimes.com/2015/01/05/books/the-girl-on-the-train-by-paula-hawkins.html", "first_chapter_link": "", "sunday_review_link": "https://www.nytimes.com/2015/02/01/books/review/the-girl-on-the-train-by-paula-hawkins.html", "article_chapter_link": "", "isbns": [{"isbn10": "1594633665", "isbn13": "9781594633669"}, {"isbn10": "0698185390", "isbn13": "9780698185395"}, {"isbn10": "1410477762", "isbn13": "9781410477767"}, {"isbn10": "0857522329", "isbn13": "9780857522320"}, {"isbn10": "1448171687", "isbn13": "9781448171682"}, {"isbn10": "1594634122", "isbn13": "9781594634123"}, {"isbn10": "038568231X", "isbn13": "9780385682312"}, {"isbn10": "1594634025", "isbn13": "9781594634024"}, {"isbn10": "0735212155", "isbn13": "9780735212152"}, {"isbn10": "0735212163", "isbn13": "9780735212169"}, {"isbn10": "1432834355", "isbn13": "9781432834357"}], "buy_links": [{"name": "Local Booksellers", "url": "http://www.indiebound.org/book/9780698185395?aff=NYT"}, {"name": "Barnes and Noble", "url": "http://www.anrdoezrs.net/click-7990613-11819508?url=http%3A%2F%2Fwww.barnesandnoble.com%2Fw%2F%3Fean%3D9780698185395"}, {"name": "Amazon", "url": "http://www.amazon.com/The-Girl-Train-A-Novel-ebook/dp/B00L9B7IKE?tag=NYTBS-20"}]}, {"rank": 2, "rank_last_week": 0, "weeks_on_list": 1, "asterisk": 0, "dagger": 0, "primary_isbn10": "1460380401", "primary_isbn13": "9781460380406", "publisher": "Mira", "description": "Grace Dillon, a champion figure skater, moved to Thunder Point to escape the ruthless world of fame and competition. But her past has caught up with her.", "price": 0, "title": "ONE WISH", "author": "Ron Carr", "contributor": "by Robyn Carr", "contributor_note": "", "book_image": "https://s1.nyt.com/du/books/images/9781460380406.jpg", "book_image_width": 128, "book_image_height": 202, "amazon_product_url": "http://www.amazon.com/Wish-Thunder-Point-Robyn-Carr-ebook/dp/B00OYBCSZG?tag=NYTBS-20", "age_group": "", "book_review_link": "", "first_chapter_link": "", "sunday_review_link": "", "article_chapter_link": "", "isbns": [{"isbn10": "0778317722", "isbn13": "9780778317722"}, {"isbn10": "1460380401", "isbn13": "9781460380406"}], "buy_links": [{"name": "Local Booksellers", "url": "http://www.indiebound.org/book/9781460380406?aff=NYT"}, {"name": "Barnes and Noble", "url": "http://www.anrdoezrs.net/click-7990613-11819508?url=http%3A%2F%2Fwww.barnesandnoble.com%2Fw%2F%3Fean%3D9781460380406"}, {"name": "Amazon", "url": "http://www.amazon.com/Wish-Thunder-Point-Robyn-Carr-ebook/dp/B00OYBCSZG?tag=NYTBS-20"}]}, {"rank": 3, "rank_last_week": 3, "weeks_on_list": 60, "asterisk": 0, "dagger": 0, "primary_isbn10": "1612130593", "primary_isbn13": "9781612130590", "publisher": "Vintage", "description": "Daunted by Christian\u2019s dark secrets, Anastasia ends their relationship \u2014 but desire still dominates her every thought; the second book in a trilogy.", "price": 0, "title": "FIFTY SHADES DARKER", "author": "E L James", "contributor": "by E. L. James", "contributor_note": "", "book_image": "https://s1.nyt.com/du/books/images/9780345803498.jpg", "book_image_width": 328, "book_image_height": 495, "amazon_product_url": "http://www.amazon.com/Fifty-Shades-Darker-E-James/dp/0345803493?tag=NYTBS-20", "age_group": "", "book_review_link": "", "first_chapter_link": "", "sunday_review_link": "", "article_chapter_link": "", "isbns": [{"isbn10": "1612130593", "isbn13": "9781612130590"}, {"isbn10": "1612130585", "isbn13": "9781612130583"}, {"isbn10": "0345803493", "isbn13": "9780345803498"}, {"isbn10": "1448149460", "isbn13": "9781448149469"}, {"isbn10": "0385363133", "isbn13": "9780385363136"}, {"isbn10": "0099579928", "isbn13": "9780099579922"}, {"isbn10": "0385537689", "isbn13": "9780385537681"}, {"isbn10": "0606264485", "isbn13": "9780606264488"}, {"isbn10": "0525431888", "isbn13": "9780525431886"}, {"isbn10": "0525434860", "isbn13": "9780525434863"}], "buy_links": [{"name": "Local Booksellers", "url": "http://www.indiebound.org/book/9781612130590?aff=NYT"}, {"name": "Barnes and Noble", "url": "http://www.anrdoezrs.net/click-7990613-11819508?url=http%3A%2F%2Fwww.barnesandnoble.com%2Fw%2F%3Fean%3D9781612130590"}, {"name": "Amazon", "url": "http://www.amazon.com/Fifty-Shades-Darker-E-James/dp/0345803493?tag=NYTBS-20"}]}, {"rank": 4, "rank_last_week": 0, "weeks_on_list": 1, "asterisk": 0, "dagger": 0, "primary_isbn10": "080417962X", "primary_isbn13": "9780804179621", "publisher": "Random House", "description": "Twins, one good and one bad, reunite after 20 years when one of them returns to their hometown. But it is no longer clear who the good and who the bad one is.", "price": 0, "title": "PRODIGAL SON", "author": "Danielle Steel", "contributor": "by Danielle Steel", "contributor_note": "", "book_image": "https://s1.nyt.com/du/books/images/9780385343152.jpg", "book_image_width": 128, "book_image_height": 194, "amazon_product_url": "http://www.amazon.com/Prodigal-Son-Novel-Danielle-Steel-ebook/dp/B00LYXV5WE?tag=NYTBS-20", "age_group": "", "book_review_link": "", "first_chapter_link": "", "sunday_review_link": "", "article_chapter_link": "", "isbns": [{"isbn10": "0385343159", "isbn13": "9780385343152"}, {"isbn10": "080417962X", "isbn13": "9780804179621"}, {"isbn10": "0804194629", "isbn13": "9780804194624"}, {"isbn10": "0440245184", "isbn13": "9780440245186"}], "buy_links": [{"name": "Local Booksellers", "url": "http://www.indiebound.org/book/9780804179621?aff=NYT"}, {"name": "Barnes and Noble", "url": "http://www.anrdoezrs.net/click-7990613-11819508?url=http%3A%2F%2Fwww.barnesandnoble.com%2Fw%2F%3Fean%3D9780804179621"}, {"name": "Amazon", "url": "http://www.amazon.com/Prodigal-Son-Novel-Danielle-Steel-ebook/dp/B00LYXV5WE?tag=NYTBS-20"}]}, {"rank": 5, "rank_last_week": 0, "weeks_on_list": 1, "asterisk": 0, "dagger": 0, "primary_isbn10": "1250034507", "primary_isbn13": "9781250034502", "publisher": "St. Martin's Press", "description": "Harry Clifton launches a campaign to release a fellow writer imprisoned in Siberia.", "price": 0, "title": "MIGHTIER THAN THE SWORD", "author": "Jeffrey Archer", "contributor": "by Jeffrey Archer", "contributor_note": "", "book_image": "https://s1.nyt.com/du/books/images/9781250034519.jpg", "book_image_width": 128, "book_image_height": 195, "amazon_product_url": "http://www.amazon.com/Mightier-than-Sword-Clifton-Chronicles/dp/1250034515?tag=NYTBS-20", "age_group": "", "book_review_link": "", "first_chapter_link": "", "sunday_review_link": "", "article_chapter_link": "", "isbns": [{"isbn10": "1250034515", "isbn13": "9781250034519"}, {"isbn10": "1250034507", "isbn13": "9781250034502"}, {"isbn10": "1410475093", "isbn13": "9781410475091"}], "buy_links": [{"name": "Local Booksellers", "url": "http://www.indiebound.org/book/9781250034502?aff=NYT"}, {"name": "Barnes and Noble", "url": "http://www.anrdoezrs.net/click-7990613-11819508?url=http%3A%2F%2Fwww.barnesandnoble.com%2Fw%2F%3Fean%3D9781250034502"}, {"name": "Amazon", "url": "http://www.amazon.com/Mightier-than-Sword-Clifton-Chronicles/dp/1250034515?tag=NYTBS-20"}]}, {"rank": 6, "rank_last_week": 2, "weeks_on_list": 79, "asterisk": 0, "dagger": 0, "primary_isbn10": "None", "primary_isbn13": "9781612130293", "publisher": "Vintage", "description": "An innocent college student falls in love with a tortured man with particular sexual tastes; the first of a trilogy.", "price": 0, "title": "FIFTY SHADES OF GREY", "author": "E L James", "contributor": "by E. L. James", "contributor_note": "", "book_image": "https://s1.nyt.com/du/books/images/9780345803481.jpg", "book_image_width": 125, "book_image_height": 193, "amazon_product_url": "http://www.amazon.com/Fifty-Shades-Grey-Book-Trilogy/dp/0345803485?tag=NYTBS-20", "age_group": "", "book_review_link": "", "first_chapter_link": "", "sunday_review_link": "", "article_chapter_link": "", "isbns": [{"isbn10": "1612130283", "isbn13": "9781612130286"}, {"isbn10": "0345803485", "isbn13": "9780345803481"}, {"isbn10": "0099579936", "isbn13": "9780099579939"}, {"isbn10": "0385363125", "isbn13": "9780385363129"}, {"isbn10": "0385537670", "isbn13": "9780385537674"}, {"isbn10": "0345806751", "isbn13": "9780345806758"}, {"isbn10": "0804172072", "isbn13": "9780804172073"}, {"isbn10": "0345805151", "isbn13": "9780345805157"}], "buy_links": [{"name": "Local Booksellers", "url": "http://www.indiebound.org/book/9781612130293?aff=NYT"}, {"name": "Barnes and Noble", "url": "http://www.anrdoezrs.net/click-7990613-11819508?url=http%3A%2F%2Fwww.barnesandnoble.com%2Fw%2F%3Fean%3D9781612130293"}, {"name": "Amazon", "url": "http://www.amazon.com/Fifty-Shades-Grey-Book-Trilogy/dp/0345803485?tag=NYTBS-20"}]}, {"rank": 7, "rank_last_week": 4, "weeks_on_list": 57, "asterisk": 0, "dagger": 0, "primary_isbn10": "1612130615", "primary_isbn13": "9781612130613", "publisher": "Vintage", "description": "Reunited, Anastasia and Christian face a world of possibilities, and unexpected challenges; the final volume in a trilogy.", "price": 0, "title": "FIFTY SHADES FREED", "author": "E L James", "contributor": "by E. L. James", "contributor_note": "", "book_image": "https://s1.nyt.com/du/books/images/9781612130606.jpg", "book_image_width": 330, "book_image_height": 495, "amazon_product_url": "http://www.amazon.com/Fifty-Shades-Freed-Three-Trilogy/dp/0345803507?tag=NYTBS-20", "age_group": "", "book_review_link": "", "first_chapter_link": "", "sunday_review_link": "", "article_chapter_link": "", "isbns": [{"isbn10": "1612130615", "isbn13": "9781612130613"}, {"isbn10": "1612130607", "isbn13": "9781612130606"}, {"isbn10": "0345803507", "isbn13": "9780345803504"}, {"isbn10": "0385537697", "isbn13": "9780385537698"}], "buy_links": [{"name": "Local Booksellers", "url": "http://www.indiebound.org/book/9781612130613?aff=NYT"}, {"name": "Barnes and Noble", "url": "http://www.anrdoezrs.net/click-7990613-11819508?url=http%3A%2F%2Fwww.barnesandnoble.com%2Fw%2F%3Fean%3D9781612130613"}, {"name": "Amazon", "url": "http://www.amazon.com/Fifty-Shades-Freed-Three-Trilogy/dp/0345803507?tag=NYTBS-20"}]}, {"rank": 8, "rank_last_week": 5, "weeks_on_list": 24, "asterisk": 0, "dagger": 0, "primary_isbn10": "", "primary_isbn13": "9781476746609", "publisher": "Scribner", "description": "The lives of a blind French girl and a gadget-obsessed German boy before and during World War II.", "price": 0, "title": "ALL THE LIGHT WE CANNOT SEE", "author": "Anthony Doerr", "contributor": "by Anthony Doerr", "contributor_note": "", "book_image": "https://s1.nyt.com/du/books/images/9781476746586.jpg", "book_image_width": 128, "book_image_height": 192, "amazon_product_url": "http://www.amazon.com/All-Light-We-Cannot-See/dp/1476746583?tag=NYTBS-20", "age_group": "", "book_review_link": "", "first_chapter_link": "", "sunday_review_link": "https://www.nytimes.com/2014/05/11/books/review/all-the-light-we-cannot-see-by-anthony-doerr.html", "article_chapter_link": "", "isbns": [{"isbn10": "1476746583", "isbn13": "9781476746586"}, {"isbn10": "1410470229", "isbn13": "9781410470225"}, {"isbn10": "1476746591", "isbn13": "9781476746593"}, {"isbn10": "1501122835", "isbn13": "9781501122835"}, {"isbn10": "0007548699", "isbn13": "9780007548699"}, {"isbn10": "1501173219", "isbn13": "9781501173219"}], "buy_links": [{"name": "Local Booksellers", "url": "http://www.indiebound.org/book/9781476746609?aff=NYT"}, {"name": "Barnes and Noble", "url": "http://www.anrdoezrs.net/click-7990613-11819508?url=http%3A%2F%2Fwww.barnesandnoble.com%2Fw%2F%3Fean%3D9781476746609"}, {"name": "Amazon", "url": "http://www.amazon.com/All-Light-We-Cannot-See/dp/1476746583?tag=NYTBS-20"}]}, {"rank": 9, "rank_last_week": 0, "weeks_on_list": 1, "asterisk": 0, "dagger": 0, "primary_isbn10": "1940218381", "primary_isbn13": "9781940218380", "publisher": "JMC Creations", "description": "Alice finds it increasingly hard to forget about her one night stand with Aiden.", "price": 0, "title": "FALLING FOR MY BEST FRIEND'S BROTHER", "author": "J S Cooper", "contributor": "by J. S. Cooper", "contributor_note": "", "book_image": "https://s1.nyt.com/du/books/images/9781940218380.jpg", "book_image_width": 330, "book_image_height": 495, "amazon_product_url": "http://www.amazon.com/Falling-For-Best-Friends-Brother-ebook/dp/B00SX587EU?tag=NYTBS-20", "age_group": "", "book_review_link": "", "first_chapter_link": "", "sunday_review_link": "", "article_chapter_link": "", "isbns": [{"isbn10": "1940218381", "isbn13": "9781940218380"}], "buy_links": [{"name": "Local Booksellers", "url": "http://www.indiebound.org/book/9781940218380?aff=NYT"}, {"name": "Barnes and Noble", "url": "http://www.anrdoezrs.net/click-7990613-11819508?url=http%3A%2F%2Fwww.barnesandnoble.com%2Fw%2F%3Fean%3D9781940218380"}, {"name": "Amazon", "url": "http://www.amazon.com/Falling-For-Best-Friends-Brother-ebook/dp/B00SX587EU?tag=NYTBS-20"}]}, {"rank": 10, "rank_last_week": 14, "weeks_on_list": 7, "asterisk": 0, "dagger": 0, "primary_isbn10": "1439157030", "primary_isbn13": "9781439157039", "publisher": "Pocket Books", "description": "A 50-year-old Harvard professor learns she has early-onset Alzheimer's disease; now a movie.", "price": 0, "title": "STILL ALICE", "author": "Lisa Genova", "contributor": "by Lisa Genova", "contributor_note": "", "book_image": "https://s1.nyt.com/du/books/images/9781439102817.jpg", "book_image_width": 128, "book_image_height": 192, "amazon_product_url": "http://www.amazon.com/Still-Alice-Lisa-Genova/dp/1439102813?tag=NYTBS-20", "age_group": "", "book_review_link": "", "first_chapter_link": "", "sunday_review_link": "", "article_chapter_link": "https://www.nytimes.com/2009/01/28/books/28selfpub.html", "isbns": [{"isbn10": "1439102813", "isbn13": "9781439102817"}, {"isbn10": "1501106422", "isbn13": "9781501106422"}, {"isbn10": "1501107739", "isbn13": "9781501107733"}, {"isbn10": "1439157030", "isbn13": "9781439157039"}, {"isbn10": "1594138567", "isbn13": "9781594138560"}], "buy_links": [{"name": "Local Booksellers", "url": "http://www.indiebound.org/book/9781439157039?aff=NYT"}, {"name": "Barnes and Noble", "url": "http://www.anrdoezrs.net/click-7990613-11819508?url=http%3A%2F%2Fwww.barnesandnoble.com%2Fw%2F%3Fean%3D9781439157039"}, {"name": "Amazon", "url": "http://www.amazon.com/Still-Alice-Lisa-Genova/dp/1439102813?tag=NYTBS-20"}]}, {"rank": 11, "rank_last_week": 7, "weeks_on_list": 4, "asterisk": 0, "dagger": 0, "primary_isbn10": "1466850604", "primary_isbn13": "9781466850606", "publisher": "St. Martin's", "description": "Two sisters are separated in World War II France: one struggling to survive in the countryside, the other joining the Resistance in Paris.", "price": 0, "title": "THE NIGHTINGALE", "author": "Kristin Hannah", "contributor": "by Kristin Hannah", "contributor_note": "", "book_image": "https://s1.nyt.com/du/books/images/9781466850606.jpg", "book_image_width": 128, "book_image_height": 195, "amazon_product_url": "http://www.amazon.com/The-Nightingale-Kristin-Hannah/dp/0312577222?tag=NYTBS-20", "age_group": "", "book_review_link": "", "first_chapter_link": "", "sunday_review_link": "", "article_chapter_link": "", "isbns": [{"isbn10": "0312577222", "isbn13": "9780312577223"}, {"isbn10": "1466850604", "isbn13": "9781466850606"}, {"isbn10": "1628995017", "isbn13": "9781628995015"}, {"isbn10": "1250080401", "isbn13": "9781250080400"}], "buy_links": [{"name": "Local Booksellers", "url": "http://www.indiebound.org/book/9781466850606?aff=NYT"}, {"name": "Barnes and Noble", "url": "http://www.anrdoezrs.net/click-7990613-11819508?url=http%3A%2F%2Fwww.barnesandnoble.com%2Fw%2F%3Fean%3D9781466850606"}, {"name": "Amazon", "url": "http://www.amazon.com/The-Nightingale-Kristin-Hannah/dp/0312577222?tag=NYTBS-20"}]}, {"rank": 12, "rank_last_week": 9, "weeks_on_list": 3, "asterisk": 0, "dagger": 0, "primary_isbn10": "1101874287", "primary_isbn13": "9781101874288", "publisher": "Knopf", "description": "Four generations of a family are drawn to a house in the Baltimore suburbs.", "price": 0, "title": "A SPOOL OF BLUE THREAD", "author": "Anne Tyler", "contributor": "by Anne Tyler", "contributor_note": "", "book_image": "https://s1.nyt.com/du/books/images/9781101874288.jpg", "book_image_width": 128, "book_image_height": 191, "amazon_product_url": "http://www.amazon.com/Spool-Blue-Thread-novel-ebook/dp/B00MSS0WVY?tag=NYTBS-20", "age_group": "", "book_review_link": "https://www.nytimes.com/2015/02/06/books/anne-tylers-20th-novel-a-spool-of-blue-thread.html", "first_chapter_link": "", "sunday_review_link": "https://www.nytimes.com/2015/02/15/books/review/a-spool-of-blue-thread-by-anne-tyler.html", "article_chapter_link": "", "isbns": [{"isbn10": "1101874279", "isbn13": "9781101874271"}, {"isbn10": "0804194726", "isbn13": "9780804194723"}, {"isbn10": "1101874287", "isbn13": "9781101874288"}, {"isbn10": "0553394398", "isbn13": "9780553394399"}], "buy_links": [{"name": "Local Booksellers", "url": "http://www.indiebound.org/book/9781101874288?aff=NYT"}, {"name": "Barnes and Noble", "url": "http://www.anrdoezrs.net/click-7990613-11819508?url=http%3A%2F%2Fwww.barnesandnoble.com%2Fw%2F%3Fean%3D9781101874288"}, {"name": "Amazon", "url": "http://www.amazon.com/Spool-Blue-Thread-novel-ebook/dp/B00MSS0WVY?tag=NYTBS-20"}]}, {"rank": 13, "rank_last_week": 6, "weeks_on_list": 118, "asterisk": 0, "dagger": 0, "primary_isbn10": "0307588386", "primary_isbn13": "9780307588388", "publisher": "Crown", "description": "A woman disappears on the day of her fifth anniversary; is her husband a killer?", "price": 0, "title": "GONE GIRL", "author": "Gillian Flynn", "contributor": "by Gillian Flynn", "contributor_note": "", "book_image": "https://s1.nyt.com/du/books/images/9780307588388.jpg", "book_image_width": 136, "book_image_height": 200, "amazon_product_url": "http://www.amazon.com/Gone-Girl-Novel-Gillian-Flynn-ebook/dp/B006LSZECO?tag=NYTBS-20", "age_group": "", "book_review_link": "https://www.nytimes.com/2012/05/30/books/gone-girl-by-gillian-flynn.html", "first_chapter_link": "", "sunday_review_link": "https://www.nytimes.com/2012/06/17/books/review/gillian-flynns-gone-girl-and-more.html", "article_chapter_link": "", "isbns": [{"isbn10": "030758836X", "isbn13": "9780307588364"}, {"isbn10": "0307588386", "isbn13": "9780307588388"}, {"isbn10": "1410450953", "isbn13": "9781410450951"}, {"isbn10": "0297859382", "isbn13": "9780297859383"}, {"isbn10": "0307588378", "isbn13": "9780307588371"}, {"isbn10": "0297859390", "isbn13": "9780297859390"}, {"isbn10": "159413605X", "isbn13": "9781594136054"}, {"isbn10": "055341836X", "isbn13": "9780553418361"}, {"isbn10": "0553418351", "isbn13": "9780553418354"}, {"isbn10": "0606270175", "isbn13": "9780606270175"}], "buy_links": [{"name": "Local Booksellers", "url": "http://www.indiebound.org/book/9780307588388?aff=NYT"}, {"name": "Barnes and Noble", "url": "http://www.anrdoezrs.net/click-7990613-11819508?url=http%3A%2F%2Fwww.barnesandnoble.com%2Fw%2F%3Fean%3D9780307588388"}, {"name": "Amazon", "url": "http://www.amazon.com/Gone-Girl-Novel-Gillian-Flynn-ebook/dp/B006LSZECO?tag=NYTBS-20"}]}, {"rank": 14, "rank_last_week": 0, "weeks_on_list": 1, "asterisk": 0, "dagger": 0, "primary_isbn10": "", "primary_isbn13": "9780062316011", "publisher": "Avon/HarperCollins", "description": "Sherry Carne thought vampires didn't exist, but one of them, Basileios Argeneau, may be her life mate.", "price": 0, "title": "THE IMMORTAL WHO LOVED ME", "author": "Lynsay Sands", "contributor": "by Lynsay Sands", "contributor_note": "", "book_image": "https://s1.nyt.com/du/books/images/9780062316004.jpg", "book_image_width": 128, "book_image_height": 206, "amazon_product_url": "http://www.amazon.com/The-Immortal-Who-Loved-Me-ebook/dp/B00HPWVW5I?tag=NYTBS-20", "age_group": "", "book_review_link": "", "first_chapter_link": "", "sunday_review_link": "", "article_chapter_link": "", "isbns": [{"isbn10": "0062316001", "isbn13": "9780062316004"}], "buy_links": [{"name": "Local Booksellers", "url": "http://www.indiebound.org/book/9780062316011?aff=NYT"}, {"name": "Barnes and Noble", "url": "http://www.anrdoezrs.net/click-7990613-11819508?url=http%3A%2F%2Fwww.barnesandnoble.com%2Fw%2F%3Fean%3D9780062316011"}, {"name": "Amazon", "url": "http://www.amazon.com/The-Immortal-Who-Loved-Me-ebook/dp/B00HPWVW5I?tag=NYTBS-20"}]}, {"rank": 15, "rank_last_week": 11, "weeks_on_list": 25, "asterisk": 0, "dagger": 0, "primary_isbn10": "0698138635", "primary_isbn13": "9780698138636", "publisher": "Amy Einhorn/Putnam", "description": "Who will end up dead, and how, when three mothers with children in the same school become friends?", "price": 0, "title": "BIG LITTLE LIES", "author": "Liane Moriarty", "contributor": "by Liane Moriarty", "contributor_note": "", "book_image": "https://s1.nyt.com/du/books/images/9780698138636.jpg", "book_image_width": 128, "book_image_height": 193, "amazon_product_url": "http://www.amazon.com/Big-Little-Lies-Liane-Moriarty-ebook/dp/B00HDMMISA?tag=NYTBS-20", "age_group": "", "book_review_link": "https://www.nytimes.com/2014/07/25/books/in-big-little-lies-liane-moriarty-finds-new-complications.html", "first_chapter_link": "", "sunday_review_link": "", "article_chapter_link": "", "isbns": [{"isbn10": "0399167064", "isbn13": "9780399167065"}, {"isbn10": "0698138635", "isbn13": "9780698138636"}, {"isbn10": "1410472035", "isbn13": "9781410472038"}, {"isbn10": "0425274861", "isbn13": "9780425274866"}, {"isbn10": "1594139067", "isbn13": "9781594139062"}, {"isbn10": "0399587195", "isbn13": "9780399587191"}, {"isbn10": "0399587209", "isbn13": "9780399587207"}, {"isbn10": "1312731796", "isbn13": "9781312731790"}], "buy_links": [{"name": "Local Booksellers", "url": "http://www.indiebound.org/book/9780698138636?aff=NYT"}, {"name": "Barnes and Noble", "url": "http://www.anrdoezrs.net/click-7990613-11819508?url=http%3A%2F%2Fwww.barnesandnoble.com%2Fw%2F%3Fean%3D9780698138636"}, {"name": "Amazon", "url": "http://www.amazon.com/Big-Little-Lies-Liane-Moriarty-ebook/dp/B00HDMMISA?tag=NYTBS-20"}]}, {"rank": 16, "rank_last_week": 0, "weeks_on_list": 0, "asterisk": 0, "dagger": 0, "primary_isbn10": "1455588814", "primary_isbn13": "9781455588817", "publisher": "Forever", "description": "", "price": 0, "title": "THOUGHTFUL", "author": "S C Stephens", "contributor": "by S. C. Stephens", "contributor_note": "", "book_image": "https://s1.nyt.com/du/books/images/9781455588817.jpg", "book_image_width": 128, "book_image_height": 195, "amazon_product_url": "http://www.amazon.com/Thoughtful-Thoughtless-S-C-Stephens-ebook/dp/B00LLIJ1DW?tag=NYTBS-20", "age_group": "", "book_review_link": "", "first_chapter_link": "", "sunday_review_link": "", "article_chapter_link": "", "isbns": [{"isbn10": "1455588814", "isbn13": "9781455588817"}, {"isbn10": "1455588822", "isbn13": "9781455588824"}], "buy_links": [{"name": "Local Booksellers", "url": "http://www.indiebound.org/book/9781455588817?aff=NYT"}, {"name": "Barnes and Noble", "url": "http://www.anrdoezrs.net/click-7990613-11819508?url=http%3A%2F%2Fwww.barnesandnoble.com%2Fw%2F%3Fean%3D9781455588817"}, {"name": "Amazon", "url": "http://www.amazon.com/Thoughtful-Thoughtless-S-C-Stephens-ebook/dp/B00LLIJ1DW?tag=NYTBS-20"}]}, {"rank": 17, "rank_last_week": 0, "weeks_on_list": 0, "asterisk": 0, "dagger": 0, "primary_isbn10": "None", "primary_isbn13": "9780698186682", "publisher": "Signet", "description": "", "price": 0, "title": "SLOW BURN", "author": "K Bromberg", "contributor": "by K. Bromberg", "contributor_note": "", "book_image": "https://s1.nyt.com/du/books/images/9780698186682.jpg", "book_image_width": 128, "book_image_height": 207, "amazon_product_url": "http://www.amazon.com/Slow-Burn-Driven-Novel-Series-ebook/dp/B00MNN7HLW?tag=NYTBS-20", "age_group": "", "book_review_link": "", "first_chapter_link": "", "sunday_review_link": "", "article_chapter_link": "", "isbns": [], "buy_links": [{"name": "Local Booksellers", "url": "http://www.indiebound.org/book/9780698186682?aff=NYT"}, {"name": "Barnes and Noble", "url": "http://www.anrdoezrs.net/click-7990613-11819508?url=http%3A%2F%2Fwww.barnesandnoble.com%2Fw%2F%3Fean%3D9780698186682"}, {"name": "Amazon", "url": "http://www.amazon.com/Slow-Burn-Driven-Novel-Series-ebook/dp/B00MNN7HLW?tag=NYTBS-20"}]}, {"rank": 18, "rank_last_week": 0, "weeks_on_list": 0, "asterisk": 0, "dagger": 0, "primary_isbn10": "None", "primary_isbn13": "9780345541383", "publisher": "Ballantine", "description": "While investigating a woman's murder, the psychologist Alex Delaware and Lt. Milo Sturgis see a link to a cold case and the possibility of a serial killer.", "price": 0, "title": "MOTIVE", "author": "Jonathan Kellerman", "contributor": "by Jonathan Kellerman", "contributor_note": "", "book_image": "https://s1.nyt.com/du/books/images/9780345541383.jpg", "book_image_width": 128, "book_image_height": 194, "amazon_product_url": "http://www.amazon.com/Motive-An-Alex-Delaware-Novel/dp/0345541375?tag=NYTBS-20", "age_group": "", "book_review_link": "", "first_chapter_link": "", "sunday_review_link": "", "article_chapter_link": "", "isbns": [{"isbn10": "0345541375", "isbn13": "9780345541376"}, {"isbn10": "0804194572", "isbn13": "9780804194570"}, {"isbn10": "0345541391", "isbn13": "9780345541390"}], "buy_links": [{"name": "Local Booksellers", "url": "http://www.indiebound.org/book/9780345541383?aff=NYT"}, {"name": "Barnes and Noble", "url": "http://www.anrdoezrs.net/click-7990613-11819508?url=http%3A%2F%2Fwww.barnesandnoble.com%2Fw%2F%3Fean%3D9780345541383"}, {"name": "Amazon", "url": "http://www.amazon.com/Motive-An-Alex-Delaware-Novel/dp/0345541375?tag=NYTBS-20"}]}, {"rank": 19, "rank_last_week": 0, "weeks_on_list": 0, "asterisk": 0, "dagger": 0, "primary_isbn10": "0316211141", "primary_isbn13": "9780316211147", "publisher": "Little, Brown", "description": "Jack Morgan, the head of an investigative firm, uncovers a murder ring in Las Vegas.", "price": 0, "title": "PRIVATE VEGAS", "author": "James Patterson and Maxine Paetro", "contributor": "by James Patterson and Maxine Paetro", "contributor_note": "", "book_image": "https://s1.nyt.com/du/books/images/9780316211147.jpg", "book_image_width": 128, "book_image_height": 200, "amazon_product_url": "http://www.amazon.com/Private-Vegas-James-Patterson/dp/031621115X?tag=NYTBS-20", "age_group": "", "book_review_link": "", "first_chapter_link": "", "sunday_review_link": "", "article_chapter_link": "", "isbns": [{"isbn10": "031621115X", "isbn13": "9780316211154"}, {"isbn10": "0316211133", "isbn13": "9780316211130"}, {"isbn10": "0316211141", "isbn13": "9780316211147"}, {"isbn10": "1455515922", "isbn13": "9781455515929"}, {"isbn10": "1455515930", "isbn13": "9781455515936"}], "buy_links": [{"name": "Local Booksellers", "url": "http://www.indiebound.org/book/9780316211147?aff=NYT"}, {"name": "Barnes and Noble", "url": "http://www.anrdoezrs.net/click-7990613-11819508?url=http%3A%2F%2Fwww.barnesandnoble.com%2Fw%2F%3Fean%3D9780316211147"}, {"name": "Amazon", "url": "http://www.amazon.com/Private-Vegas-James-Patterson/dp/031621115X?tag=NYTBS-20"}]}, {"rank": 20, "rank_last_week": 0, "weeks_on_list": 0, "asterisk": 0, "dagger": 0, "primary_isbn10": "146038041X", "primary_isbn13": "9781460380413", "publisher": "Mira", "description": "", "price": 0, "title": "THE GIRLS OF MISCHIEF BAY", "author": "Susan Mallery", "contributor": "by Susan Mallery", "contributor_note": "", "book_image": "https://s1.nyt.com/du/books/images/9781460380413.jpg", "book_image_width": 128, "book_image_height": 196, "amazon_product_url": "http://www.amazon.com/The-Girls-Mischief-Susan-Mallery-ebook/dp/B00OYAG0AG?tag=NYTBS-20", "age_group": "", "book_review_link": "", "first_chapter_link": "", "sunday_review_link": "", "article_chapter_link": "", "isbns": [{"isbn10": "146038041X", "isbn13": "9781460380413"}, {"isbn10": "0778317749", "isbn13": "9780778317746"}, {"isbn10": "0778316025", "isbn13": "9780778316022"}], "buy_links": [{"name": "Local Booksellers", "url": "http://www.indiebound.org/book/9781460380413?aff=NYT"}, {"name": "Barnes and Noble", "url": "http://www.anrdoezrs.net/click-7990613-11819508?url=http%3A%2F%2Fwww.barnesandnoble.com%2Fw%2F%3Fean%3D9781460380413"}, {"name": "Amazon", "url": "http://www.amazon.com/The-Girls-Mischief-Susan-Mallery-ebook/dp/B00OYAG0AG?tag=NYTBS-20"}]}], "corrections": []}}