{"status": "OK", "copyright": "Copyright (c) 2019 The New York Times Company.  All Rights Reserved.", "num_results": 20, "last_modified": "2017-03-21T13:38:01-04:00", "results": {"list_name": "Combined Print and E-Book Fiction", "list_name_encoded": "combined-print-and-e-book-fiction", "bestsellers_date": "2016-03-05", "published_date": "2016-03-20", "published_date_description": "", "next_published_date": "2016-03-27", "previous_published_date": "2016-03-13", "display_name": "Combined Print & E-Book Fiction", "normal_list_ends_at": 15, "updated": "WEEKLY", "books": [{"rank": 1, "rank_last_week": 0, "weeks_on_list": 1, "asterisk": 0, "dagger": 0, "primary_isbn10": "0698406427", "primary_isbn13": "9780698406421", "publisher": "Putnam", "description": "In the ninth book in this series, set in 1906, the New York detective Isaac Bell contends with a crime boss passing as a respectable businessman and a tycoon\u2019s plot against President Theodore Roosevelt.", "price": 0, "title": "THE GANGSTER", "author": "Clive Cussler and Justin Scott", "contributor": "by Clive Cussler and Justin Scott", "contributor_note": "", "book_image": "https://s1.nyt.com/du/books/images/9780399175954.jpg", "book_image_width": 328, "book_image_height": 495, "amazon_product_url": "http://www.amazon.com/The-Gangster-Isaac-Bell-Adventure/dp/0399175954?tag=NYTBS-20", "age_group": "", "book_review_link": "", "first_chapter_link": "", "sunday_review_link": "", "article_chapter_link": "", "isbns": [{"isbn10": "0399175954", "isbn13": "9780399175954"}, {"isbn10": "0698406427", "isbn13": "9780698406421"}], "buy_links": [{"name": "Local Booksellers", "url": "http://www.indiebound.org/book/9780698406421?aff=NYT"}, {"name": "Barnes and Noble", "url": "http://www.anrdoezrs.net/click-7990613-11819508?url=http%3A%2F%2Fwww.barnesandnoble.com%2Fw%2F%3Fean%3D9780698406421"}, {"name": "Amazon", "url": "http://www.amazon.com/The-Gangster-Isaac-Bell-Adventure/dp/0399175954?tag=NYTBS-20"}]}, {"rank": 2, "rank_last_week": 1, "weeks_on_list": 5, "asterisk": 0, "dagger": 0, "primary_isbn10": "0143124544", "primary_isbn13": "9780143124542", "publisher": "Penguin", "description": "A woman who has barely been beyond her English village finds herself while caring for a wealthy, embittered quadriplegic.", "price": 0, "title": "ME BEFORE YOU", "author": "Jojo Moyes", "contributor": "by Jojo Moyes", "contributor_note": "", "book_image": "https://s1.nyt.com/du/books/images/9780143124542.jpg", "book_image_width": 323, "book_image_height": 495, "amazon_product_url": "http://www.amazon.com/Me-Before-You-A-Novel/dp/0143124544?tag=NYTBS-20", "age_group": "", "book_review_link": "", "first_chapter_link": "", "sunday_review_link": "https://www.nytimes.com/2013/01/06/books/review/me-before-you-by-jojo-moyes.html", "article_chapter_link": "", "isbns": [{"isbn10": "0670026603", "isbn13": "9780670026609"}, {"isbn10": "0143124544", "isbn13": "9780143124542"}, {"isbn10": "1594137390", "isbn13": "9781594137396"}, {"isbn10": "0143109464", "isbn13": "9780143109464"}, {"isbn10": "0143130153", "isbn13": "9780143130154"}], "buy_links": [{"name": "Local Booksellers", "url": "http://www.indiebound.org/book/9780143124542?aff=NYT"}, {"name": "Barnes and Noble", "url": "http://www.anrdoezrs.net/click-7990613-11819508?url=http%3A%2F%2Fwww.barnesandnoble.com%2Fw%2F%3Fean%3D9780143124542"}, {"name": "Amazon", "url": "http://www.amazon.com/Me-Before-You-A-Novel/dp/0143124544?tag=NYTBS-20"}]}, {"rank": 3, "rank_last_week": 0, "weeks_on_list": 11, "asterisk": 0, "dagger": 0, "primary_isbn10": "0316129119", "primary_isbn13": "9780316129114", "publisher": "Little, Brown", "description": "The entire world of the 5-year-old boy who narrates this novel is the 11-by-11-foot room in which his mother is being held prisoner.", "price": 0, "title": "ROOM", "author": "Emma Donoghue", "contributor": "by Emma Donoghue", "contributor_note": "", "book_image": "https://s1.nyt.com/du/books/images/9780316223232.jpg", "book_image_width": 313, "book_image_height": 495, "amazon_product_url": "http://www.amazon.com/Room-A-Novel-Emma-Donoghue/dp/0316098329?tag=NYTBS-20", "age_group": "", "book_review_link": "https://www.nytimes.com/2010/09/13/books/13book.html", "first_chapter_link": "", "sunday_review_link": "https://www.nytimes.com/2010/09/19/books/review/Bender-t.html", "article_chapter_link": "", "isbns": [{"isbn10": "0316098337", "isbn13": "9780316098335"}, {"isbn10": "0316129119", "isbn13": "9780316129114"}, {"isbn10": "0316098329", "isbn13": "9780316098328"}, {"isbn10": "0316223239", "isbn13": "9780316223232"}, {"isbn10": "0316391344", "isbn13": "9780316391344"}, {"isbn10": "0330519026", "isbn13": "9780330519021"}, {"isbn10": "0316268356", "isbn13": "9780316268356"}], "buy_links": [{"name": "Local Booksellers", "url": "http://www.indiebound.org/book/9780316129114?aff=NYT"}, {"name": "Barnes and Noble", "url": "http://www.anrdoezrs.net/click-7990613-11819508?url=http%3A%2F%2Fwww.barnesandnoble.com%2Fw%2F%3Fean%3D9780316129114"}, {"name": "Amazon", "url": "http://www.amazon.com/Room-A-Novel-Emma-Donoghue/dp/0316098329?tag=NYTBS-20"}]}, {"rank": 4, "rank_last_week": 5, "weeks_on_list": 45, "asterisk": 0, "dagger": 0, "primary_isbn10": "1466850604", "primary_isbn13": "9781466850606", "publisher": "St. Martin's", "description": "Two sisters are separated in World War II France: one in the countryside, the other in Paris.", "price": 0, "title": "THE NIGHTINGALE", "author": "Kristin Hannah", "contributor": "by Kristin Hannah", "contributor_note": "", "book_image": "https://s1.nyt.com/du/books/images/9781466850606.jpg", "book_image_width": 128, "book_image_height": 195, "amazon_product_url": "http://www.amazon.com/The-Nightingale-Kristin-Hannah/dp/0312577222?tag=NYTBS-20", "age_group": "", "book_review_link": "", "first_chapter_link": "", "sunday_review_link": "", "article_chapter_link": "", "isbns": [{"isbn10": "0312577222", "isbn13": "9780312577223"}, {"isbn10": "1466850604", "isbn13": "9781466850606"}, {"isbn10": "1628995017", "isbn13": "9781628995015"}, {"isbn10": "1250080401", "isbn13": "9781250080400"}], "buy_links": [{"name": "Local Booksellers", "url": "http://www.indiebound.org/book/9781466850606?aff=NYT"}, {"name": "Barnes and Noble", "url": "http://www.anrdoezrs.net/click-7990613-11819508?url=http%3A%2F%2Fwww.barnesandnoble.com%2Fw%2F%3Fean%3D9781466850606"}, {"name": "Amazon", "url": "http://www.amazon.com/The-Nightingale-Kristin-Hannah/dp/0312577222?tag=NYTBS-20"}]}, {"rank": 5, "rank_last_week": 6, "weeks_on_list": 2, "asterisk": 0, "dagger": 0, "primary_isbn10": "1401686311", "primary_isbn13": "9781401686314", "publisher": "Thomas Nelson", "description": "With her own wedding approaching, Charlotte pieces together the history of a vintage gown she finds.", "price": 0, "title": "THE WEDDING DRESS", "author": "Rachel Hauck", "contributor": "by Rachel Hauck", "contributor_note": "", "book_image": "https://s1.nyt.com/du/books/images/9781401686314.jpg", "book_image_width": 325, "book_image_height": 495, "amazon_product_url": "http://www.amazon.com/The-Wedding-Dress-Rachel-Hauck-ebook/dp/B005ENBASO?tag=NYTBS-20", "age_group": "", "book_review_link": "", "first_chapter_link": "", "sunday_review_link": "", "article_chapter_link": "", "isbns": [{"isbn10": "1401686311", "isbn13": "9781401686314"}, {"isbn10": "1595549633", "isbn13": "9781595549631"}, {"isbn10": "0718077954", "isbn13": "9780718077952"}], "buy_links": [{"name": "Local Booksellers", "url": "http://www.indiebound.org/book/9781401686314?aff=NYT"}, {"name": "Barnes and Noble", "url": "http://www.anrdoezrs.net/click-7990613-11819508?url=http%3A%2F%2Fwww.barnesandnoble.com%2Fw%2F%3Fean%3D9781401686314"}, {"name": "Amazon", "url": "http://www.amazon.com/The-Wedding-Dress-Rachel-Hauck-ebook/dp/B005ENBASO?tag=NYTBS-20"}]}, {"rank": 6, "rank_last_week": 8, "weeks_on_list": 57, "asterisk": 0, "dagger": 0, "primary_isbn10": "1594633665", "primary_isbn13": "9781594633669", "publisher": "Riverhead", "description": "A psychological thriller set in the environs of London is full of complications and betrayals.", "price": 0, "title": "THE GIRL ON THE TRAIN", "author": "Paula Hawkins", "contributor": "by Paula Hawkins", "contributor_note": "", "book_image": "https://s1.nyt.com/du/books/images/9781594633669.jpg", "book_image_width": 312, "book_image_height": 495, "amazon_product_url": "http://www.amazon.com/The-Girl-Train-A-Novel-ebook/dp/B00L9B7IKE?tag=NYTBS-20", "age_group": "", "book_review_link": "https://www.nytimes.com/2015/01/05/books/the-girl-on-the-train-by-paula-hawkins.html", "first_chapter_link": "", "sunday_review_link": "https://www.nytimes.com/2015/02/01/books/review/the-girl-on-the-train-by-paula-hawkins.html", "article_chapter_link": "", "isbns": [{"isbn10": "1594633665", "isbn13": "9781594633669"}, {"isbn10": "0698185390", "isbn13": "9780698185395"}, {"isbn10": "1410477762", "isbn13": "9781410477767"}, {"isbn10": "0857522329", "isbn13": "9780857522320"}, {"isbn10": "1448171687", "isbn13": "9781448171682"}, {"isbn10": "1594634122", "isbn13": "9781594634123"}, {"isbn10": "038568231X", "isbn13": "9780385682312"}, {"isbn10": "1594634025", "isbn13": "9781594634024"}, {"isbn10": "0735212155", "isbn13": "9780735212152"}, {"isbn10": "0735212163", "isbn13": "9780735212169"}, {"isbn10": "1432834355", "isbn13": "9781432834357"}], "buy_links": [{"name": "Local Booksellers", "url": "http://www.indiebound.org/book/9781594633669?aff=NYT"}, {"name": "Barnes and Noble", "url": "http://www.anrdoezrs.net/click-7990613-11819508?url=http%3A%2F%2Fwww.barnesandnoble.com%2Fw%2F%3Fean%3D9781594633669"}, {"name": "Amazon", "url": "http://www.amazon.com/The-Girl-Train-A-Novel-ebook/dp/B00L9B7IKE?tag=NYTBS-20"}]}, {"rank": 7, "rank_last_week": 0, "weeks_on_list": 2, "asterisk": 0, "dagger": 0, "primary_isbn10": "1466842040", "primary_isbn13": "9781466842045", "publisher": "St. Martin's", "description": "A father hides a terrible secret to protect his son.", "price": 0, "title": "KEEP QUIET", "author": "Lisa Scottoline", "contributor": "by Lisa Scottoline", "contributor_note": "", "book_image": "https://s1.nyt.com/du/books/images/9781250010094.jpg", "book_image_width": 128, "book_image_height": 195, "amazon_product_url": "http://www.amazon.com/Keep-Quiet-Lisa-Scottoline-ebook/dp/B00FIL9BCE?tag=NYTBS-20", "age_group": "", "book_review_link": "", "first_chapter_link": "", "sunday_review_link": "", "article_chapter_link": "", "isbns": [{"isbn10": "1250010098", "isbn13": "9781250010094"}, {"isbn10": "1466842040", "isbn13": "9781466842045"}, {"isbn10": "1250010101", "isbn13": "9781250010100"}], "buy_links": [{"name": "Local Booksellers", "url": "http://www.indiebound.org/book/9781466842045?aff=NYT"}, {"name": "Barnes and Noble", "url": "http://www.anrdoezrs.net/click-7990613-11819508?url=http%3A%2F%2Fwww.barnesandnoble.com%2Fw%2F%3Fean%3D9781466842045"}, {"name": "Amazon", "url": "http://www.amazon.com/Keep-Quiet-Lisa-Scottoline-ebook/dp/B00FIL9BCE?tag=NYTBS-20"}]}, {"rank": 8, "rank_last_week": 0, "weeks_on_list": 1, "asterisk": 0, "dagger": 0, "primary_isbn10": "1439160120", "primary_isbn13": "9781439160121", "publisher": "Touchstone", "description": "An Irish orphan is integrated into a slave family on a Virginia plantation.", "price": 0, "title": "THE KITCHEN HOUSE", "author": "Kathleen Grissom", "contributor": "by Kathleen Grissom", "contributor_note": "", "book_image": "https://s1.nyt.com/du/books/images/9781439153666.jpg", "book_image_width": 185, "book_image_height": 277, "amazon_product_url": "http://www.amazon.com/The-Kitchen-House-A-Novel/dp/1439153663?tag=NYTBS-20", "age_group": "", "book_review_link": "", "first_chapter_link": "", "sunday_review_link": "", "article_chapter_link": "", "isbns": [{"isbn10": "1439153663", "isbn13": "9781439153666"}, {"isbn10": "1410444627", "isbn13": "9781410444622"}, {"isbn10": "1439160120", "isbn13": "9781439160121"}], "buy_links": [{"name": "Local Booksellers", "url": "http://www.indiebound.org/book/9781439160121?aff=NYT"}, {"name": "Barnes and Noble", "url": "http://www.anrdoezrs.net/click-7990613-11819508?url=http%3A%2F%2Fwww.barnesandnoble.com%2Fw%2F%3Fean%3D9781439160121"}, {"name": "Amazon", "url": "http://www.amazon.com/The-Kitchen-House-A-Novel/dp/1439153663?tag=NYTBS-20"}]}, {"rank": 9, "rank_last_week": 14, "weeks_on_list": 75, "asterisk": 0, "dagger": 0, "primary_isbn10": "1476746583", "primary_isbn13": "9781476746586", "publisher": "Scribner", "description": "The lives of a blind French girl and a gadget-obsessed German boy before and during World War II.", "price": 0, "title": "ALL THE LIGHT WE CANNOT SEE", "author": "Anthony Doerr", "contributor": "by Anthony Doerr", "contributor_note": "", "book_image": "https://s1.nyt.com/du/books/images/9781476746586.jpg", "book_image_width": 128, "book_image_height": 192, "amazon_product_url": "http://www.amazon.com/All-Light-We-Cannot-See/dp/1476746583?tag=NYTBS-20", "age_group": "", "book_review_link": "", "first_chapter_link": "", "sunday_review_link": "https://www.nytimes.com/2014/05/11/books/review/all-the-light-we-cannot-see-by-anthony-doerr.html", "article_chapter_link": "", "isbns": [{"isbn10": "1476746583", "isbn13": "9781476746586"}, {"isbn10": "1410470229", "isbn13": "9781410470225"}, {"isbn10": "1476746591", "isbn13": "9781476746593"}, {"isbn10": "1501122835", "isbn13": "9781501122835"}, {"isbn10": "0007548699", "isbn13": "9780007548699"}, {"isbn10": "1501173219", "isbn13": "9781501173219"}], "buy_links": [{"name": "Local Booksellers", "url": "http://www.indiebound.org/book/9781476746586?aff=NYT"}, {"name": "Barnes and Noble", "url": "http://www.anrdoezrs.net/click-7990613-11819508?url=http%3A%2F%2Fwww.barnesandnoble.com%2Fw%2F%3Fean%3D9781476746586"}, {"name": "Amazon", "url": "http://www.amazon.com/All-Light-We-Cannot-See/dp/1476746583?tag=NYTBS-20"}]}, {"rank": 10, "rank_last_week": 0, "weeks_on_list": 7, "asterisk": 0, "dagger": 0, "primary_isbn10": "1101989750", "primary_isbn13": "9781101989753", "publisher": "Putnam", "description": "A woman returning to her hometown discovers that her husband was a fraud who implicated her in his deceptions.", "price": 0, "title": "THE LIAR", "author": "Nora Roberts", "contributor": "by Nora Roberts", "contributor_note": "", "book_image": "https://s1.nyt.com/du/books/images/9780698161351.jpg", "book_image_width": 328, "book_image_height": 495, "amazon_product_url": "http://www.amazon.com/The-Liar-Nora-Roberts-ebook/dp/B00O2BKKZS?tag=NYTBS-20", "age_group": "", "book_review_link": "", "first_chapter_link": "", "sunday_review_link": "", "article_chapter_link": "", "isbns": [{"isbn10": "0399170863", "isbn13": "9780399170867"}, {"isbn10": "0399175865", "isbn13": "9780399175862"}, {"isbn10": "1101989750", "isbn13": "9781101989753"}, {"isbn10": "0425279154", "isbn13": "9780425279151"}], "buy_links": [{"name": "Local Booksellers", "url": "http://www.indiebound.org/book/9781101989753?aff=NYT"}, {"name": "Barnes and Noble", "url": "http://www.anrdoezrs.net/click-7990613-11819508?url=http%3A%2F%2Fwww.barnesandnoble.com%2Fw%2F%3Fean%3D9781101989753"}, {"name": "Amazon", "url": "http://www.amazon.com/The-Liar-Nora-Roberts-ebook/dp/B00O2BKKZS?tag=NYTBS-20"}]}, {"rank": 11, "rank_last_week": 13, "weeks_on_list": 4, "asterisk": 0, "dagger": 0, "primary_isbn10": "069840422X", "primary_isbn13": "9780698404229", "publisher": "Dutton", "description": "The detective D. \u2009D. Warren hunts for a missing woman who was kidnapped and abused as a student and may have become a vigilante.", "price": 0, "title": "FIND HER", "author": "Lisa Gardner", "contributor": "by Lisa Gardner", "contributor_note": "", "book_image": "https://s1.nyt.com/du/books/images/9780525954576.jpg", "book_image_width": 328, "book_image_height": 495, "amazon_product_url": "http://www.amazon.com/Find-Her-Lisa-Gardner/dp/0525954570?tag=NYTBS-20", "age_group": "", "book_review_link": "", "first_chapter_link": "", "sunday_review_link": "", "article_chapter_link": "", "isbns": [{"isbn10": "0525954570", "isbn13": "9780525954576"}, {"isbn10": "069840422X", "isbn13": "9780698404229"}, {"isbn10": "0451477162", "isbn13": "9780451477163"}], "buy_links": [{"name": "Local Booksellers", "url": "http://www.indiebound.org/book/9780698404229?aff=NYT"}, {"name": "Barnes and Noble", "url": "http://www.anrdoezrs.net/click-7990613-11819508?url=http%3A%2F%2Fwww.barnesandnoble.com%2Fw%2F%3Fean%3D9780698404229"}, {"name": "Amazon", "url": "http://www.amazon.com/Find-Her-Lisa-Gardner/dp/0525954570?tag=NYTBS-20"}]}, {"rank": 12, "rank_last_week": 0, "weeks_on_list": 10, "asterisk": 0, "dagger": 0, "primary_isbn10": "1455559806", "primary_isbn13": "9781455559800", "publisher": "Grand Central", "description": "A police detective who left the force when his family was murdered teams up with his former partner to solve the case.", "price": 0, "title": "MEMORY MAN", "author": "David Baldacci", "contributor": "by David Baldacci", "contributor_note": "", "book_image": "https://s1.nyt.com/du/books/images/9781455586387.jpg", "book_image_width": 330, "book_image_height": 490, "amazon_product_url": "http://www.amazon.com/Memory-Amos-Decker-David-Baldacci-ebook/dp/B00N7TDP8K?tag=NYTBS-20", "age_group": "", "book_review_link": "", "first_chapter_link": "", "sunday_review_link": "", "article_chapter_link": "", "isbns": [{"isbn10": "1455559822", "isbn13": "9781455559824"}, {"isbn10": "1455589489", "isbn13": "9781455589487"}, {"isbn10": "1455586382", "isbn13": "9781455586387"}, {"isbn10": "1455559814", "isbn13": "9781455559817"}, {"isbn10": "1455559806", "isbn13": "9781455559800"}], "buy_links": [{"name": "Local Booksellers", "url": "http://www.indiebound.org/book/9781455559800?aff=NYT"}, {"name": "Barnes and Noble", "url": "http://www.anrdoezrs.net/click-7990613-11819508?url=http%3A%2F%2Fwww.barnesandnoble.com%2Fw%2F%3Fean%3D9781455559800"}, {"name": "Amazon", "url": "http://www.amazon.com/Memory-Amos-Decker-David-Baldacci-ebook/dp/B00N7TDP8K?tag=NYTBS-20"}]}, {"rank": 13, "rank_last_week": 0, "weeks_on_list": 8, "asterisk": 0, "dagger": 0, "primary_isbn10": "1250072689", "primary_isbn13": "9781250072689", "publisher": "Picador", "description": "Left for dead after a mauling, a master tracker is consumed by a singular desire for revenge; an inspiration for the 2015 film.", "price": 0, "title": "THE REVENANT", "author": "Michael Punke", "contributor": "by Michael Punke", "contributor_note": "", "book_image": "https://s1.nyt.com/du/books/images/9781250101198.jpg", "book_image_width": 330, "book_image_height": 494, "amazon_product_url": "http://www.amazon.com/The-Revenant-A-Novel-Revenge/dp/1250101190?tag=NYTBS-20", "age_group": "", "book_review_link": "", "first_chapter_link": "", "sunday_review_link": "", "article_chapter_link": "", "isbns": [{"isbn10": "1250101190", "isbn13": "9781250101198"}, {"isbn10": "1250072689", "isbn13": "9781250072689"}, {"isbn10": "1250066638", "isbn13": "9781250066633"}, {"isbn10": "125006662X", "isbn13": "9781250066626"}], "buy_links": [{"name": "Local Booksellers", "url": "http://www.indiebound.org/book/9781250072689?aff=NYT"}, {"name": "Barnes and Noble", "url": "http://www.anrdoezrs.net/click-7990613-11819508?url=http%3A%2F%2Fwww.barnesandnoble.com%2Fw%2F%3Fean%3D9781250072689"}, {"name": "Amazon", "url": "http://www.amazon.com/The-Revenant-A-Novel-Revenge/dp/1250101190?tag=NYTBS-20"}]}, {"rank": 14, "rank_last_week": 0, "weeks_on_list": 40, "asterisk": 0, "dagger": 0, "primary_isbn10": "0553418025", "primary_isbn13": "9780553418026", "publisher": "Crown", "description": "Abandoned by his crew, an astronaut embarks on a dogged quest to stay alive.", "price": 0, "title": "THE MARTIAN", "author": "Andy Weir", "contributor": "by Andy Weir", "contributor_note": "", "book_image": "https://s1.nyt.com/du/books/images/9780804139038.jpg", "book_image_width": 128, "book_image_height": 194, "amazon_product_url": "http://www.amazon.com/The-Martian-Novel-Andy-Weir-ebook/dp/B00EMXBDMA?tag=NYTBS-20", "age_group": "", "book_review_link": "", "first_chapter_link": "", "sunday_review_link": "", "article_chapter_link": "", "isbns": [{"isbn10": "0804139024", "isbn13": "9780804139021"}, {"isbn10": "0553418025", "isbn13": "9780553418026"}, {"isbn10": "0091956145", "isbn13": "9780091956141"}, {"isbn10": "1594138540", "isbn13": "9781594138546"}, {"isbn10": "1101903589", "isbn13": "9781101903582"}, {"isbn10": "110190500X", "isbn13": "9781101905005"}], "buy_links": [{"name": "Local Booksellers", "url": "http://www.indiebound.org/book/9780553418026?aff=NYT"}, {"name": "Barnes and Noble", "url": "http://www.anrdoezrs.net/click-7990613-11819508?url=http%3A%2F%2Fwww.barnesandnoble.com%2Fw%2F%3Fean%3D9780553418026"}, {"name": "Amazon", "url": "http://www.amazon.com/The-Martian-Novel-Andy-Weir-ebook/dp/B00EMXBDMA?tag=NYTBS-20"}]}, {"rank": 15, "rank_last_week": 0, "weeks_on_list": 1, "asterisk": 0, "dagger": 0, "primary_isbn10": "1501106473", "primary_isbn13": "9781501106477", "publisher": "Scribner", "description": "An unsophisticated young Irishwoman leaves her home for New York in the 1950s. The basis of the movie.", "price": 0, "title": "BROOKLYN", "author": "Colm Toibin", "contributor": "by Colm Toibin", "contributor_note": "", "book_image": "https://s1.nyt.com/du/books/images/9781439138311.jpg", "book_image_width": 140, "book_image_height": 211, "amazon_product_url": "http://www.amazon.com/Brooklyn-A-Novel-Colm-Toibin/dp/1439138311?tag=NYTBS-20", "age_group": "", "book_review_link": "", "first_chapter_link": "https://www.nytimes.com/2009/05/03/books/chapter-brooklyn.html", "sunday_review_link": "https://www.nytimes.com/2009/05/03/books/review/Schillinger-t.html", "article_chapter_link": "https://www.nytimes.com/2009/05/03/magazine/03toibin-t.html", "isbns": [{"isbn10": "1439148953", "isbn13": "9781439148952"}, {"isbn10": "1501106473", "isbn13": "9781501106477"}, {"isbn10": "1439149828", "isbn13": "9781439149829"}, {"isbn10": "1439138311", "isbn13": "9781439138311"}], "buy_links": [{"name": "Local Booksellers", "url": "http://www.indiebound.org/book/9781501106477?aff=NYT"}, {"name": "Barnes and Noble", "url": "http://www.anrdoezrs.net/click-7990613-11819508?url=http%3A%2F%2Fwww.barnesandnoble.com%2Fw%2F%3Fean%3D9781501106477"}, {"name": "Amazon", "url": "http://www.amazon.com/Brooklyn-A-Novel-Colm-Toibin/dp/1439138311?tag=NYTBS-20"}]}, {"rank": 16, "rank_last_week": 0, "weeks_on_list": 0, "asterisk": 0, "dagger": 0, "primary_isbn10": "1101990465", "primary_isbn13": "9781101990469", "publisher": "New American Library", "description": "When a suspect in a missing-child case dies, reporters and the police wrongly think they\u2019ll get the real story from his widow.", "price": 0, "title": "THE WIDOW", "author": "Fiona Barton", "contributor": "by Fiona Barton", "contributor_note": "", "book_image": "https://s1.nyt.com/du/books/images/9781101990469.jpg", "book_image_width": 328, "book_image_height": 495, "amazon_product_url": "http://www.amazon.com/The-Widow-Fiona-Barton-ebook/dp/B00Z8VT8AE?tag=NYTBS-20", "age_group": "", "book_review_link": "", "first_chapter_link": "", "sunday_review_link": "", "article_chapter_link": "", "isbns": [{"isbn10": "1101990260", "isbn13": "9781101990261"}, {"isbn10": "1101990465", "isbn13": "9781101990469"}, {"isbn10": "1101990473", "isbn13": "9781101990476"}], "buy_links": [{"name": "Local Booksellers", "url": "http://www.indiebound.org/book/9781101990469?aff=NYT"}, {"name": "Barnes and Noble", "url": "http://www.anrdoezrs.net/click-7990613-11819508?url=http%3A%2F%2Fwww.barnesandnoble.com%2Fw%2F%3Fean%3D9781101990469"}, {"name": "Amazon", "url": "http://www.amazon.com/The-Widow-Fiona-Barton-ebook/dp/B00Z8VT8AE?tag=NYTBS-20"}]}, {"rank": 17, "rank_last_week": 0, "weeks_on_list": 0, "asterisk": 0, "dagger": 0, "primary_isbn10": "1501131222", "primary_isbn13": "9781501131226", "publisher": "Gallery", "description": "Will Sumner and Hanna Bergstrom find that a wedding and everlasting love were just the beginning.", "price": 0, "title": "BEAUTIFUL BOSS", "author": "Christina Lauren", "contributor": "by Christina Lauren", "contributor_note": "", "book_image": "https://s1.nyt.com/du/books/images/9781501131226.jpg", "book_image_width": 318, "book_image_height": 495, "amazon_product_url": "http://www.amazon.com/Beautiful-Boss-The-Series-Book-ebook/dp/B010MH19GO?tag=NYTBS-20", "age_group": "", "book_review_link": "", "first_chapter_link": "", "sunday_review_link": "", "article_chapter_link": "", "isbns": [{"isbn10": "1501131222", "isbn13": "9781501131226"}, {"isbn10": "150114622X", "isbn13": "9781501146220"}], "buy_links": [{"name": "Local Booksellers", "url": "http://www.indiebound.org/book/9781501131226?aff=NYT"}, {"name": "Barnes and Noble", "url": "http://www.anrdoezrs.net/click-7990613-11819508?url=http%3A%2F%2Fwww.barnesandnoble.com%2Fw%2F%3Fean%3D9781501131226"}, {"name": "Amazon", "url": "http://www.amazon.com/Beautiful-Boss-The-Series-Book-ebook/dp/B010MH19GO?tag=NYTBS-20"}]}, {"rank": 18, "rank_last_week": 0, "weeks_on_list": 0, "asterisk": 0, "dagger": 0, "primary_isbn10": "0553391925", "primary_isbn13": "9780553391923", "publisher": "Ballantine", "description": "A mother and her daughter-in-law both leave unhappy marriages and take up with new men.", "price": 0, "title": "A GIRL'S GUIDE TO MOVING ON", "author": "Debbie Macomber", "contributor": "by Debbie Macomber", "contributor_note": "", "book_image": "https://s1.nyt.com/du/books/images/9780553391930.jpg", "book_image_width": 326, "book_image_height": 495, "amazon_product_url": "http://www.amazon.com/Girls-Guide-Moving-On-Novel-ebook/dp/B00ZNE17B4?tag=NYTBS-20", "age_group": "", "book_review_link": "", "first_chapter_link": "", "sunday_review_link": "", "article_chapter_link": "", "isbns": [{"isbn10": "0553391925", "isbn13": "9780553391923"}, {"isbn10": "0553391933", "isbn13": "9780553391930"}, {"isbn10": "0399566821", "isbn13": "9780399566820"}, {"isbn10": "0553391941", "isbn13": "9780553391947"}], "buy_links": [{"name": "Local Booksellers", "url": "http://www.indiebound.org/book/9780553391923?aff=NYT"}, {"name": "Barnes and Noble", "url": "http://www.anrdoezrs.net/click-7990613-11819508?url=http%3A%2F%2Fwww.barnesandnoble.com%2Fw%2F%3Fean%3D9780553391923"}, {"name": "Amazon", "url": "http://www.amazon.com/Girls-Guide-Moving-On-Novel-ebook/dp/B00ZNE17B4?tag=NYTBS-20"}]}, {"rank": 19, "rank_last_week": 0, "weeks_on_list": 0, "asterisk": 0, "dagger": 0, "primary_isbn10": "1466867507", "primary_isbn13": "9781466867505", "publisher": "St. Martin's", "description": "The sixth and penultimate book of the Clifton Chronicles brings the Cliftons and the Barringtons into the 1970s.", "price": 0, "title": "COMETH THE HOUR", "author": "Jeffrey Archer", "contributor": "by Jeffrey Archer", "contributor_note": "", "book_image": "https://s1.nyt.com/du/books/images/9781466867505.jpg", "book_image_width": 327, "book_image_height": 495, "amazon_product_url": "http://www.amazon.com/Cometh-Hour-Novel-Clifton-Chronicles-ebook/dp/B00YWZU0MC?tag=NYTBS-20", "age_group": "", "book_review_link": "", "first_chapter_link": "", "sunday_review_link": "", "article_chapter_link": "", "isbns": [{"isbn10": "1250061628", "isbn13": "9781250061621"}, {"isbn10": "1466867507", "isbn13": "9781466867505"}, {"isbn10": "125006161X", "isbn13": "9781250061614"}, {"isbn10": "1250091780", "isbn13": "9781250091789"}], "buy_links": [{"name": "Local Booksellers", "url": "http://www.indiebound.org/book/9781466867505?aff=NYT"}, {"name": "Barnes and Noble", "url": "http://www.anrdoezrs.net/click-7990613-11819508?url=http%3A%2F%2Fwww.barnesandnoble.com%2Fw%2F%3Fean%3D9781466867505"}, {"name": "Amazon", "url": "http://www.amazon.com/Cometh-Hour-Novel-Clifton-Chronicles-ebook/dp/B00YWZU0MC?tag=NYTBS-20"}]}, {"rank": 20, "rank_last_week": 0, "weeks_on_list": 0, "asterisk": 0, "dagger": 0, "primary_isbn10": "0062328948", "primary_isbn13": "9780062328946", "publisher": "Morrow", "description": "Defending an innocent young man, the defense attorney Paul Madriani uncovers a morass of corruption and greed that leads to the highest levels of political power.", "price": 0, "title": "THE ENEMY INSIDE", "author": "Steve Martini", "contributor": "by Steve Martini", "contributor_note": "", "book_image": "https://s1.nyt.com/du/books/images/9780062328946.jpg", "book_image_width": 328, "book_image_height": 495, "amazon_product_url": "http://www.amazon.com/The-Enemy-Inside-Madriani-Novels-ebook/dp/B00MTSC7LG?tag=NYTBS-20", "age_group": "", "book_review_link": "", "first_chapter_link": "", "sunday_review_link": "", "article_chapter_link": "", "isbns": [{"isbn10": "0062328948", "isbn13": "9780062328946"}, {"isbn10": "006232893X", "isbn13": "9780062328939"}, {"isbn10": "0062328956", "isbn13": "9780062328953"}], "buy_links": [{"name": "Local Booksellers", "url": "http://www.indiebound.org/book/9780062328946?aff=NYT"}, {"name": "Barnes and Noble", "url": "http://www.anrdoezrs.net/click-7990613-11819508?url=http%3A%2F%2Fwww.barnesandnoble.com%2Fw%2F%3Fean%3D9780062328946"}, {"name": "Amazon", "url": "http://www.amazon.com/The-Enemy-Inside-Madriani-Novels-ebook/dp/B00MTSC7LG?tag=NYTBS-20"}]}], "corrections": []}}