{"status": "OK", "copyright": "Copyright (c) 2019 The New York Times Company.  All Rights Reserved.", "num_results": 20, "last_modified": "2016-04-28T15:03:27-04:00", "results": {"list_name": "Combined Print and E-Book Fiction", "list_name_encoded": "combined-print-and-e-book-fiction", "bestsellers_date": "2014-10-04", "published_date": "2014-10-19", "published_date_description": "", "next_published_date": "2014-10-26", "previous_published_date": "2014-10-12", "display_name": "Combined Print & E-Book Fiction", "normal_list_ends_at": 15, "updated": "WEEKLY", "books": [{"rank": 1, "rank_last_week": 1, "weeks_on_list": 97, "asterisk": 0, "dagger": 0, "primary_isbn10": "0307588386", "primary_isbn13": "9780307588388", "publisher": "Crown", "description": "A woman disappears on the day of her fifth anniversary; is her husband a killer?", "price": 0, "title": "GONE GIRL", "author": "Gillian Flynn", "contributor": "by Gillian Flynn", "contributor_note": "", "book_image": "https://s1.nyt.com/du/books/images/9780307588388.jpg", "book_image_width": 136, "book_image_height": 200, "amazon_product_url": "http://www.amazon.com/Gone-Girl-Novel-Gillian-Flynn-ebook/dp/B006LSZECO?tag=NYTBS-20", "age_group": "", "book_review_link": "https://www.nytimes.com/2012/05/30/books/gone-girl-by-gillian-flynn.html", "first_chapter_link": "", "sunday_review_link": "https://www.nytimes.com/2012/06/17/books/review/gillian-flynns-gone-girl-and-more.html", "article_chapter_link": "", "isbns": [{"isbn10": "030758836X", "isbn13": "9780307588364"}, {"isbn10": "0307588386", "isbn13": "9780307588388"}, {"isbn10": "1410450953", "isbn13": "9781410450951"}, {"isbn10": "0297859382", "isbn13": "9780297859383"}, {"isbn10": "0307588378", "isbn13": "9780307588371"}, {"isbn10": "0297859390", "isbn13": "9780297859390"}, {"isbn10": "159413605X", "isbn13": "9781594136054"}, {"isbn10": "055341836X", "isbn13": "9780553418361"}, {"isbn10": "0553418351", "isbn13": "9780553418354"}, {"isbn10": "0606270175", "isbn13": "9780606270175"}], "buy_links": [{"name": "Local Booksellers", "url": "http://www.indiebound.org/book/9780307588388?aff=NYT"}, {"name": "Barnes and Noble", "url": "http://www.anrdoezrs.net/click-7990613-11819508?url=http%3A%2F%2Fwww.barnesandnoble.com%2Fw%2F%3Fean%3D9780307588388"}, {"name": "Amazon", "url": "http://www.amazon.com/Gone-Girl-Novel-Gillian-Flynn-ebook/dp/B006LSZECO?tag=NYTBS-20"}]}, {"rank": 2, "rank_last_week": 0, "weeks_on_list": 1, "asterisk": 0, "dagger": 0, "primary_isbn10": "0316211028", "primary_isbn13": "9780316211024", "publisher": "Little, Brown", "description": "Detective Michael Bennett, back in New York City, investigates a peculiar crime in Harlem.", "price": 0, "title": "BURN", "author": "James Patterson and Michael Ledwidge", "contributor": "by James Patterson and Michael Ledwidge", "contributor_note": "", "book_image": "https://s1.nyt.com/du/books/images/9780316211024.jpg", "book_image_width": 128, "book_image_height": 198, "amazon_product_url": "http://www.amazon.com/Burn-Michael-Bennett-James-Patterson/dp/0316211044?tag=NYTBS-20", "age_group": "", "book_review_link": "", "first_chapter_link": "", "sunday_review_link": "", "article_chapter_link": "", "isbns": [{"isbn10": "0316211044", "isbn13": "9780316211048"}, {"isbn10": "0316410632", "isbn13": "9780316410632"}, {"isbn10": "0316211028", "isbn13": "9780316211024"}, {"isbn10": "1455515876", "isbn13": "9781455515875"}, {"isbn10": "1455515868", "isbn13": "9781455515868"}], "buy_links": [{"name": "Local Booksellers", "url": "http://www.indiebound.org/book/9780316211024?aff=NYT"}, {"name": "Barnes and Noble", "url": "http://www.anrdoezrs.net/click-7990613-11819508?url=http%3A%2F%2Fwww.barnesandnoble.com%2Fw%2F%3Fean%3D9780316211024"}, {"name": "Amazon", "url": "http://www.amazon.com/Burn-Michael-Bennett-James-Patterson/dp/0316211044?tag=NYTBS-20"}]}, {"rank": 3, "rank_last_week": 0, "weeks_on_list": 1, "asterisk": 0, "dagger": 0, "primary_isbn10": "1101618752", "primary_isbn13": "9781101618752", "publisher": "Putnam", "description": "Nicholas Drummond of Scotland Yard, now an F.B.I. agent, investigates a Wall Street stabbing that involves secrets reaching back to World War I.", "price": 0, "title": "THE LOST KEY", "author": "Catherine Coulter and J T Ellison", "contributor": "by Catherine Coulter and J. T. Ellison", "contributor_note": "", "book_image": "https://s1.nyt.com/du/books/images/9781101618752.jpg", "book_image_width": 128, "book_image_height": 194, "amazon_product_url": "http://www.amazon.com/The-Lost-Key-Brit-FBI/dp/0399164766?tag=NYTBS-20", "age_group": "", "book_review_link": "", "first_chapter_link": "", "sunday_review_link": "", "article_chapter_link": "", "isbns": [{"isbn10": "0399164766", "isbn13": "9780399164767"}, {"isbn10": "1101618752", "isbn13": "9781101618752"}, {"isbn10": "0515155802", "isbn13": "9780515155808"}], "buy_links": [{"name": "Local Booksellers", "url": "http://www.indiebound.org/book/9781101618752?aff=NYT"}, {"name": "Barnes and Noble", "url": "http://www.anrdoezrs.net/click-7990613-11819508?url=http%3A%2F%2Fwww.barnesandnoble.com%2Fw%2F%3Fean%3D9781101618752"}, {"name": "Amazon", "url": "http://www.amazon.com/The-Lost-Key-Brit-FBI/dp/0399164766?tag=NYTBS-20"}]}, {"rank": 4, "rank_last_week": 4, "weeks_on_list": 5, "asterisk": 0, "dagger": 0, "primary_isbn10": "None", "primary_isbn13": "9781455502547", "publisher": "Grand Central", "description": "Twenty-five years after their high school romance ended, two classmates return to their North Carolina town for a funeral.", "price": 0, "title": "THE BEST OF ME", "author": "Nicholas Sparks", "contributor": "by Nicholas Sparks", "contributor_note": "", "book_image": "https://s1.nyt.com/du/books/images/9780446547642.jpg", "book_image_width": 185, "book_image_height": 280, "amazon_product_url": "http://www.amazon.com/The-Best-Me-Nicholas-Sparks/dp/0446547646?tag=NYTBS-20", "age_group": "", "book_review_link": "", "first_chapter_link": "", "sunday_review_link": "", "article_chapter_link": "", "isbns": [{"isbn10": "0446547654", "isbn13": "9780446547659"}, {"isbn10": "0446547646", "isbn13": "9780446547642"}, {"isbn10": "1455504106", "isbn13": "9781455504107"}, {"isbn10": "0446547638", "isbn13": "9780446547635"}, {"isbn10": "1455556556", "isbn13": "9781455556557"}, {"isbn10": "1455556564", "isbn13": "9781455556564"}], "buy_links": [{"name": "Local Booksellers", "url": "http://www.indiebound.org/book/9781455502547?aff=NYT"}, {"name": "Barnes and Noble", "url": "http://www.anrdoezrs.net/click-7990613-11819508?url=http%3A%2F%2Fwww.barnesandnoble.com%2Fw%2F%3Fean%3D9781455502547"}, {"name": "Amazon", "url": "http://www.amazon.com/The-Best-Me-Nicholas-Sparks/dp/0446547646?tag=NYTBS-20"}]}, {"rank": 5, "rank_last_week": 2, "weeks_on_list": 3, "asterisk": 0, "dagger": 0, "primary_isbn10": "0698160576", "primary_isbn13": "9780698160576", "publisher": "Dutton", "description": "Five interrelated families grapple with the events of the 1960s through the 1980s; Book 3 of the Century Trilogy.\u00a0", "price": 0, "title": "EDGE OF ETERNITY", "author": "Ken Follett", "contributor": "by Ken Follett", "contributor_note": "", "book_image": "https://s1.nyt.com/du/books/images/9780525953098.jpg", "book_image_width": 128, "book_image_height": 194, "amazon_product_url": "http://www.amazon.com/Edge-Eternity-Three-Century-Trilogy/dp/0525953094?tag=NYTBS-20", "age_group": "", "book_review_link": "", "first_chapter_link": "", "sunday_review_link": "", "article_chapter_link": "", "isbns": [{"isbn10": "0525953094", "isbn13": "9780525953098"}, {"isbn10": "0698160576", "isbn13": "9780698160576"}, {"isbn10": "1410475468", "isbn13": "9781410475466"}, {"isbn10": "0451474015", "isbn13": "9780451474018"}, {"isbn10": "0451474023", "isbn13": "9780451474025"}], "buy_links": [{"name": "Local Booksellers", "url": "http://www.indiebound.org/book/9780698160576?aff=NYT"}, {"name": "Barnes and Noble", "url": "http://www.anrdoezrs.net/click-7990613-11819508?url=http%3A%2F%2Fwww.barnesandnoble.com%2Fw%2F%3Fean%3D9780698160576"}, {"name": "Amazon", "url": "http://www.amazon.com/Edge-Eternity-Three-Century-Trilogy/dp/0525953094?tag=NYTBS-20"}]}, {"rank": 6, "rank_last_week": 5, "weeks_on_list": 10, "asterisk": 0, "dagger": 0, "primary_isbn10": "0440335167", "primary_isbn13": "9780440335160", "publisher": "Dell", "description": "Claire Randall, an English nurse, is transported back to 1743 during a second honeymoon in the Scottish Highlands.", "price": 0, "title": "OUTLANDER", "author": "Diana Gabaldon", "contributor": "by Diana Gabaldon", "contributor_note": "", "book_image": "https://s1.nyt.com/du/books/images/9780440212560.jpg", "book_image_width": 301, "book_image_height": 495, "amazon_product_url": "http://www.amazon.com/Outlander-Diana-Gabaldon/dp/0440212561?tag=NYTBS-20", "age_group": "", "book_review_link": "", "first_chapter_link": "", "sunday_review_link": "", "article_chapter_link": "", "isbns": [{"isbn10": "0440335167", "isbn13": "9780440335160"}, {"isbn10": "0440212561", "isbn13": "9780440212560"}, {"isbn10": "0385319959", "isbn13": "9780385319959"}, {"isbn10": "0553393693", "isbn13": "9780553393699"}, {"isbn10": "0553393707", "isbn13": "9780553393705"}, {"isbn10": "0440423201", "isbn13": "9780440423201"}, {"isbn10": "0385302304", "isbn13": "9780385302302"}], "buy_links": [{"name": "Local Booksellers", "url": "http://www.indiebound.org/book/9780440335160?aff=NYT"}, {"name": "Barnes and Noble", "url": "http://www.anrdoezrs.net/click-7990613-11819508?url=http%3A%2F%2Fwww.barnesandnoble.com%2Fw%2F%3Fean%3D9780440335160"}, {"name": "Amazon", "url": "http://www.amazon.com/Outlander-Diana-Gabaldon/dp/0440212561?tag=NYTBS-20"}]}, {"rank": 7, "rank_last_week": 0, "weeks_on_list": 1, "asterisk": 0, "dagger": 0, "primary_isbn10": "1942215037", "primary_isbn13": "9781942215035", "publisher": "Penelope Ward", "description": "A bond, and an attraction, between two stepsiblings.", "price": 0, "title": "STEPBROTHER DEAREST", "author": "Penelope Ward", "contributor": "by Penelope Ward", "contributor_note": "", "book_image": "https://s1.nyt.com/du/books/images/9781942215035.jpg", "book_image_width": 328, "book_image_height": 495, "amazon_product_url": "http://www.amazon.com/Stepbrother-Dearest-Penelope-Ward-ebook/dp/B00NVY6JPC?tag=NYTBS-20", "age_group": "", "book_review_link": "", "first_chapter_link": "", "sunday_review_link": "", "article_chapter_link": "", "isbns": [{"isbn10": "1942215037", "isbn13": "9781942215035"}, {"isbn10": "1942215045", "isbn13": "9781942215042"}], "buy_links": [{"name": "Local Booksellers", "url": "http://www.indiebound.org/book/9781942215035?aff=NYT"}, {"name": "Barnes and Noble", "url": "http://www.anrdoezrs.net/click-7990613-11819508?url=http%3A%2F%2Fwww.barnesandnoble.com%2Fw%2F%3Fean%3D9781942215035"}, {"name": "Amazon", "url": "http://www.amazon.com/Stepbrother-Dearest-Penelope-Ward-ebook/dp/B00NVY6JPC?tag=NYTBS-20"}]}, {"rank": 8, "rank_last_week": 3, "weeks_on_list": 5, "asterisk": 0, "dagger": 0, "primary_isbn10": "0804178763", "primary_isbn13": "9780804178761", "publisher": "Delacorte", "description": "Jack Reacher, a former military cop, helps the State Department and the C.I.A. stop a sniper who has targeted a G8 summit.\u00a0", "price": 0, "title": "PERSONAL", "author": "Lee Child", "contributor": "by Lee Child", "contributor_note": "", "book_image": "https://s1.nyt.com/du/books/images/9780804178747.jpg", "book_image_width": 128, "book_image_height": 194, "amazon_product_url": "http://www.amazon.com/Personal-Jack-Reacher-Lee-Child/dp/0804178747?tag=NYTBS-20", "age_group": "", "book_review_link": "", "first_chapter_link": "", "sunday_review_link": "", "article_chapter_link": "", "isbns": [{"isbn10": "0804178747", "isbn13": "9780804178747"}, {"isbn10": "0804178763", "isbn13": "9780804178761"}, {"isbn10": "1473508770", "isbn13": "9781473508774"}, {"isbn10": "0804178755", "isbn13": "9780804178754"}], "buy_links": [{"name": "Local Booksellers", "url": "http://www.indiebound.org/book/9780804178761?aff=NYT"}, {"name": "Barnes and Noble", "url": "http://www.anrdoezrs.net/click-7990613-11819508?url=http%3A%2F%2Fwww.barnesandnoble.com%2Fw%2F%3Fean%3D9780804178761"}, {"name": "Amazon", "url": "http://www.amazon.com/Personal-Jack-Reacher-Lee-Child/dp/0804178747?tag=NYTBS-20"}]}, {"rank": 9, "rank_last_week": 11, "weeks_on_list": 6, "asterisk": 0, "dagger": 0, "primary_isbn10": "0440335183", "primary_isbn13": "9780440335184", "publisher": "Dell", "description": "Volume 2 of the Outlander series, about an 18th-century Scottish warrior and a time-traveling World War II-era nurse; first published in 1992.", "price": 0, "title": "DRAGONFLY IN AMBER", "author": "Diana Gabaldon", "contributor": "by Diana Gabaldon", "contributor_note": "", "book_image": "https://s1.nyt.com/du/books/images/9780440335184.jpg", "book_image_width": 314, "book_image_height": 475, "amazon_product_url": "http://www.amazon.com/Dragonfly-Amber-Outlander-Book-2-ebook/dp/B000FC2L28?tag=NYTBS-20", "age_group": "", "book_review_link": "", "first_chapter_link": "", "sunday_review_link": "", "article_chapter_link": "", "isbns": [{"isbn10": "0440215625", "isbn13": "9780440215622"}, {"isbn10": "0440335183", "isbn13": "9780440335184"}, {"isbn10": "0385335970", "isbn13": "9780385335973"}], "buy_links": [{"name": "Local Booksellers", "url": "http://www.indiebound.org/book/9780440335184?aff=NYT"}, {"name": "Barnes and Noble", "url": "http://www.anrdoezrs.net/click-7990613-11819508?url=http%3A%2F%2Fwww.barnesandnoble.com%2Fw%2F%3Fean%3D9780440335184"}, {"name": "Amazon", "url": "http://www.amazon.com/Dragonfly-Amber-Outlander-Book-2-ebook/dp/B000FC2L28?tag=NYTBS-20"}]}, {"rank": 10, "rank_last_week": 8, "weeks_on_list": 10, "asterisk": 0, "dagger": 0, "primary_isbn10": "0698138635", "primary_isbn13": "9780698138636", "publisher": "Amy Einhorn/Putnam", "description": "Who will end up dead, and how, when three mothers with children in the same school become friends?", "price": 0, "title": "BIG LITTLE LIES", "author": "Liane Moriarty", "contributor": "by Liane Moriarty", "contributor_note": "", "book_image": "https://s1.nyt.com/du/books/images/9780698138636.jpg", "book_image_width": 128, "book_image_height": 193, "amazon_product_url": "http://www.amazon.com/Big-Little-Lies-Liane-Moriarty-ebook/dp/B00HDMMISA?tag=NYTBS-20", "age_group": "", "book_review_link": "https://www.nytimes.com/2014/07/25/books/in-big-little-lies-liane-moriarty-finds-new-complications.html", "first_chapter_link": "", "sunday_review_link": "", "article_chapter_link": "", "isbns": [{"isbn10": "0399167064", "isbn13": "9780399167065"}, {"isbn10": "0698138635", "isbn13": "9780698138636"}, {"isbn10": "1410472035", "isbn13": "9781410472038"}, {"isbn10": "0425274861", "isbn13": "9780425274866"}, {"isbn10": "1594139067", "isbn13": "9781594139062"}, {"isbn10": "0399587195", "isbn13": "9780399587191"}, {"isbn10": "0399587209", "isbn13": "9780399587207"}, {"isbn10": "1312731796", "isbn13": "9781312731790"}], "buy_links": [{"name": "Local Booksellers", "url": "http://www.indiebound.org/book/9780698138636?aff=NYT"}, {"name": "Barnes and Noble", "url": "http://www.anrdoezrs.net/click-7990613-11819508?url=http%3A%2F%2Fwww.barnesandnoble.com%2Fw%2F%3Fean%3D9780698138636"}, {"name": "Amazon", "url": "http://www.amazon.com/Big-Little-Lies-Liane-Moriarty-ebook/dp/B00HDMMISA?tag=NYTBS-20"}]}, {"rank": 11, "rank_last_week": 0, "weeks_on_list": 1, "asterisk": 0, "dagger": 0, "primary_isbn10": "None", "primary_isbn13": "9781250020062", "publisher": "St. Martin's", "description": "A teenager with psychic abilities is rescued by a mysterious man who has a task for her.", "price": 0, "title": "THE PERFECT WITNESS", "author": "Iris Johansen", "contributor": "by Iris Johansen", "contributor_note": "", "book_image": "https://s1.nyt.com/du/books/images/9781250020062.jpg", "book_image_width": 128, "book_image_height": 194, "amazon_product_url": "http://www.amazon.com/The-Perfect-Witness-Iris-Johansen-ebook/dp/B00J6U7LPM?tag=NYTBS-20", "age_group": "", "book_review_link": "", "first_chapter_link": "", "sunday_review_link": "", "article_chapter_link": "", "isbns": [{"isbn10": "1250020050", "isbn13": "9781250020055"}, {"isbn10": "1250067243", "isbn13": "9781250067241"}], "buy_links": [{"name": "Local Booksellers", "url": "http://www.indiebound.org/book/9781250020062?aff=NYT"}, {"name": "Barnes and Noble", "url": "http://www.anrdoezrs.net/click-7990613-11819508?url=http%3A%2F%2Fwww.barnesandnoble.com%2Fw%2F%3Fean%3D9781250020062"}, {"name": "Amazon", "url": "http://www.amazon.com/The-Perfect-Witness-Iris-Johansen-ebook/dp/B00J6U7LPM?tag=NYTBS-20"}]}, {"rank": 12, "rank_last_week": 0, "weeks_on_list": 1, "asterisk": 0, "dagger": 0, "primary_isbn10": "150110442X", "primary_isbn13": "9781501104428", "publisher": "Scribner", "description": "An unsuspecting accountant's wife makes a disturbing discovery; first published in 2010, now a movie.", "price": 0, "title": "A GOOD MARRIAGE", "author": "Stephen King", "contributor": "by Stephen King", "contributor_note": "", "book_image": "https://s1.nyt.com/du/books/images/9781501104428.jpg", "book_image_width": 128, "book_image_height": 192, "amazon_product_url": "http://www.amazon.com/A-Good-Marriage-Stephen-King-ebook/dp/B00NJXK37U?tag=NYTBS-20", "age_group": "", "book_review_link": "", "first_chapter_link": "", "sunday_review_link": "", "article_chapter_link": "", "isbns": [{"isbn10": "150110442X", "isbn13": "9781501104428"}], "buy_links": [{"name": "Local Booksellers", "url": "http://www.indiebound.org/book/9781501104428?aff=NYT"}, {"name": "Barnes and Noble", "url": "http://www.anrdoezrs.net/click-7990613-11819508?url=http%3A%2F%2Fwww.barnesandnoble.com%2Fw%2F%3Fean%3D9781501104428"}, {"name": "Amazon", "url": "http://www.amazon.com/A-Good-Marriage-Stephen-King-ebook/dp/B00NJXK37U?tag=NYTBS-20"}]}, {"rank": 13, "rank_last_week": 0, "weeks_on_list": 1, "asterisk": 0, "dagger": 0, "primary_isbn10": "1460340248", "primary_isbn13": "9781460340240", "publisher": "Harlequin", "description": "Will Emmaline's date to her ex-fianc\u00e9's wedding turn into more?", "price": 0, "title": "IN YOUR DREAMS", "author": "Kristan Higgins", "contributor": "by Kristan Higgins", "contributor_note": "", "book_image": "https://s1.nyt.com/du/books/images/9781460340240.jpg", "book_image_width": 128, "book_image_height": 203, "amazon_product_url": "http://www.amazon.com/Your-Dreams-Blue-Heron-Series/dp/0373779313?tag=NYTBS-20", "age_group": "", "book_review_link": "", "first_chapter_link": "", "sunday_review_link": "", "article_chapter_link": "", "isbns": [{"isbn10": "0373779313", "isbn13": "9780373779314"}, {"isbn10": "1460340248", "isbn13": "9781460340240"}], "buy_links": [{"name": "Local Booksellers", "url": "http://www.indiebound.org/book/9781460340240?aff=NYT"}, {"name": "Barnes and Noble", "url": "http://www.anrdoezrs.net/click-7990613-11819508?url=http%3A%2F%2Fwww.barnesandnoble.com%2Fw%2F%3Fean%3D9781460340240"}, {"name": "Amazon", "url": "http://www.amazon.com/Your-Dreams-Blue-Heron-Series/dp/0373779313?tag=NYTBS-20"}]}, {"rank": 14, "rank_last_week": 0, "weeks_on_list": 1, "asterisk": 0, "dagger": 0, "primary_isbn10": "0307459926", "primary_isbn13": "9780307459923", "publisher": "Broadway", "description": "A woman who, as a child, was spared when her mother and sisters were murdered begins to reinvestigate the case against her imprisoned brother.", "price": 0, "title": "DARK PLACES", "author": "Gillian Flynn", "contributor": "by Gillian Flynn", "contributor_note": "", "book_image": "https://s1.nyt.com/du/books/images/9780307341570.jpg", "book_image_width": 302, "book_image_height": 495, "amazon_product_url": "http://www.amazon.com/Dark-Places-Novel-Gillian-Flynn/dp/0307341577?tag=NYTBS-20", "age_group": "", "book_review_link": "", "first_chapter_link": "", "sunday_review_link": "", "article_chapter_link": "", "isbns": [{"isbn10": "0307459926", "isbn13": "9780307459923"}, {"isbn10": "0307341577", "isbn13": "9780307341570"}, {"isbn10": "1101902884", "isbn13": "9781101902882"}, {"isbn10": "0553418483", "isbn13": "9780553418484"}], "buy_links": [{"name": "Local Booksellers", "url": "http://www.indiebound.org/book/9780307459923?aff=NYT"}, {"name": "Barnes and Noble", "url": "http://www.anrdoezrs.net/click-7990613-11819508?url=http%3A%2F%2Fwww.barnesandnoble.com%2Fw%2F%3Fean%3D9780307459923"}, {"name": "Amazon", "url": "http://www.amazon.com/Dark-Places-Novel-Gillian-Flynn/dp/0307341577?tag=NYTBS-20"}]}, {"rank": 15, "rank_last_week": 0, "weeks_on_list": 1, "asterisk": 0, "dagger": 0, "primary_isbn10": "None", "primary_isbn13": "A00B00NOCBOUG", "publisher": "Harper Sloan", "description": "Emmy loves Maddox, but his demons may destroy both of them; a Corps Security novel.", "price": 0, "title": "LOCKE", "author": "Harper Sloan", "contributor": "by Harper Sloan", "contributor_note": "", "book_image": "https://s1.nyt.com/du/books/images/A00B00NOCBOUG.jpg", "book_image_width": 330, "book_image_height": 495, "amazon_product_url": "http://www.amazon.com/Locke-Corps-Security-Book-6-ebook/dp/B00NOCBOUG?tag=NYTBS-20", "age_group": "", "book_review_link": "", "first_chapter_link": "", "sunday_review_link": "", "article_chapter_link": "", "isbns": [], "buy_links": [{"name": "Local Booksellers", "url": "http://www.indiebound.org/search/book?searchfor=LOCKE+Harper+Sloan&aff=NYT"}, {"name": "Barnes and Noble", "url": "http://www.anrdoezrs.net/click-7990613-11819508?url=http%3A%2F%2Fwww.barnesandnoble.com%2Fs%2FLOCKE+Harper+Sloan"}, {"name": "Amazon", "url": "http://www.amazon.com/Locke-Corps-Security-Book-6-ebook/dp/B00NOCBOUG?tag=NYTBS-20"}]}, {"rank": 16, "rank_last_week": 0, "weeks_on_list": 0, "asterisk": 0, "dagger": 0, "primary_isbn10": "None", "primary_isbn13": "A00B00I88BUTQ", "publisher": "Jessica Sorensen", "description": "", "price": 0, "title": "THE RESOLUTION OF CALLIE AND KAYDEN", "author": "Jessica Sorensen", "contributor": "by Jessica Sorensen", "contributor_note": "", "book_image": "https://s1.nyt.com/du/books/images/A00B00I88BUTQ.jpg", "book_image_width": 325, "book_image_height": 495, "amazon_product_url": "http://www.amazon.com/Resolution-Callie-Kayden-Coincidence-Book-ebook/dp/B00I88BUTQ?tag=NYTBS-20", "age_group": "", "book_review_link": "", "first_chapter_link": "", "sunday_review_link": "", "article_chapter_link": "", "isbns": [], "buy_links": [{"name": "Local Booksellers", "url": "http://www.indiebound.org/search/book?searchfor=THE+RESOLUTION+OF+CALLIE+AND+KAYDEN+Jessica+Sorensen&aff=NYT"}, {"name": "Barnes and Noble", "url": "http://www.anrdoezrs.net/click-7990613-11819508?url=http%3A%2F%2Fwww.barnesandnoble.com%2Fs%2FTHE+RESOLUTION+OF+CALLIE+AND+KAYDEN+Jessica+Sorensen"}, {"name": "Amazon", "url": "http://www.amazon.com/Resolution-Callie-Kayden-Coincidence-Book-ebook/dp/B00I88BUTQ?tag=NYTBS-20"}]}, {"rank": 17, "rank_last_week": 0, "weeks_on_list": 0, "asterisk": 0, "dagger": 0, "primary_isbn10": "None", "primary_isbn13": "9780553419894", "publisher": "Broadway", "description": "", "price": 0, "title": "THE COMPLETE GILLIAN FLYNN", "author": "Gillian Flynn", "contributor": "by Gillian Flynn", "contributor_note": "", "book_image": "https://s1.nyt.com/du/books/images/9780553419894.jpg", "book_image_width": 128, "book_image_height": 199, "amazon_product_url": "http://www.amazon.com/The-Complete-Gillian-Flynn-Objects-ebook/dp/B00JNQMKT6?tag=NYTBS-20", "age_group": "", "book_review_link": "", "first_chapter_link": "", "sunday_review_link": "", "article_chapter_link": "", "isbns": [], "buy_links": [{"name": "Local Booksellers", "url": "http://www.indiebound.org/book/9780553419894?aff=NYT"}, {"name": "Barnes and Noble", "url": "http://www.anrdoezrs.net/click-7990613-11819508?url=http%3A%2F%2Fwww.barnesandnoble.com%2Fw%2F%3Fean%3D9780553419894"}, {"name": "Amazon", "url": "http://www.amazon.com/The-Complete-Gillian-Flynn-Objects-ebook/dp/B00JNQMKT6?tag=NYTBS-20"}]}, {"rank": 18, "rank_last_week": 0, "weeks_on_list": 0, "asterisk": 0, "dagger": 0, "primary_isbn10": "", "primary_isbn13": "9780062101204", "publisher": "Morrow/HarperCollins", "description": "A historical novel about orphans swept off the streets of New York and sent to the Midwest in the 1920s.", "price": 0, "title": "ORPHAN TRAIN", "author": "Christina Baker Kline", "contributor": "by Christina Baker Kline", "contributor_note": "", "book_image": "https://s1.nyt.com/du/books/images/9780062101204.jpg", "book_image_width": 329, "book_image_height": 495, "amazon_product_url": "http://www.amazon.com/Orphan-Train-Christina-Baker-Kline-ebook/dp/B0089LOG02?tag=NYTBS-20", "age_group": "", "book_review_link": "", "first_chapter_link": "", "sunday_review_link": "", "article_chapter_link": "", "isbns": [{"isbn10": "0061950726", "isbn13": "9780061950728"}, {"isbn10": "1594137374", "isbn13": "9781594137372"}, {"isbn10": "0606356649", "isbn13": "9780606356640"}, {"isbn10": "006195070X", "isbn13": "9780061950704"}], "buy_links": [{"name": "Local Booksellers", "url": "http://www.indiebound.org/book/9780062101204?aff=NYT"}, {"name": "Barnes and Noble", "url": "http://www.anrdoezrs.net/click-7990613-11819508?url=http%3A%2F%2Fwww.barnesandnoble.com%2Fw%2F%3Fean%3D9780062101204"}, {"name": "Amazon", "url": "http://www.amazon.com/Orphan-Train-Christina-Baker-Kline-ebook/dp/B0089LOG02?tag=NYTBS-20"}]}, {"rank": 19, "rank_last_week": 0, "weeks_on_list": 0, "asterisk": 0, "dagger": 0, "primary_isbn10": "None", "primary_isbn13": "9781940921266", "publisher": "Gossamer", "description": "", "price": 0, "title": "HOLIDAY TREASURE", "author": "Melody Anne", "contributor": "by Melody Anne", "contributor_note": "", "book_image": "https://s1.nyt.com/du/books/images/9781940921266.jpg", "book_image_width": 128, "book_image_height": 192, "amazon_product_url": "http://www.amazon.com/Holiday-Treasure-Billionaire-Bachelors-Book-ebook/dp/B00KJ2R7ZA?tag=NYTBS-20", "age_group": "", "book_review_link": "", "first_chapter_link": "", "sunday_review_link": "", "article_chapter_link": "", "isbns": [], "buy_links": [{"name": "Local Booksellers", "url": "http://www.indiebound.org/book/9781940921266?aff=NYT"}, {"name": "Barnes and Noble", "url": "http://www.anrdoezrs.net/click-7990613-11819508?url=http%3A%2F%2Fwww.barnesandnoble.com%2Fw%2F%3Fean%3D9781940921266"}, {"name": "Amazon", "url": "http://www.amazon.com/Holiday-Treasure-Billionaire-Bachelors-Book-ebook/dp/B00KJ2R7ZA?tag=NYTBS-20"}]}, {"rank": 20, "rank_last_week": 0, "weeks_on_list": 0, "asterisk": 0, "dagger": 0, "primary_isbn10": "None", "primary_isbn13": "9780991418268", "publisher": "HTJB", "description": "", "price": 0, "title": "KISSES AFTER DARK", "author": "Marie Force", "contributor": "by Marie Force", "contributor_note": "", "book_image": "https://s1.nyt.com/du/books/images/9780991418268.jpg", "book_image_width": 128, "book_image_height": 189, "amazon_product_url": "http://www.amazon.com/Kisses-McCarthys-Gansett-Island-Series-ebook/dp/B00NAKAAV6?tag=NYTBS-20", "age_group": "", "book_review_link": "", "first_chapter_link": "", "sunday_review_link": "", "article_chapter_link": "", "isbns": [], "buy_links": [{"name": "Local Booksellers", "url": "http://www.indiebound.org/book/9780991418268?aff=NYT"}, {"name": "Barnes and Noble", "url": "http://www.anrdoezrs.net/click-7990613-11819508?url=http%3A%2F%2Fwww.barnesandnoble.com%2Fw%2F%3Fean%3D9780991418268"}, {"name": "Amazon", "url": "http://www.amazon.com/Kisses-McCarthys-Gansett-Island-Series-ebook/dp/B00NAKAAV6?tag=NYTBS-20"}]}], "corrections": []}}